Workbook

Sheet Reorg Summary
A1: PMS Questionnaire Reorganization – Executive & KPI Focus
A2: The active catalogue retains simple/direct questions with tags, replaces recoverable empty-table dependencies, defers unsupported modules, and adds high-value executive/KPI questions based on populated tables.
A5: Metric | B5: Count | D5: Complexity | E5: Count
A6: Active questionnaire questions | B6: =COUNTA('Reorganized Questionnaire'!I:I)-1 | D6: Simple | E6: =COUNTIF('Reorganized Questionnaire'!G:G,"Simple")
A7: Retained or reworked existing questions | B7: =COUNTIF('Reorganized Questionnaire'!A:A,"Existing*") | D7: Moderate | E7: =COUNTIF('Reorganized Questionnaire'!G:G,"Moderate")
A8: New executive/KPI questions | B8: =COUNTIF('Reorganized Questionnaire'!A:A,"New*") | D8: Complex | E8: =COUNTIF('Reorganized Questionnaire'!G:G,"Complex")
A9: Deferred due to empty tables | B9: =COUNTA('Deferred Empty Tables'!A:A)-1 | D9: Very Complex | E9: =COUNTIF('Reorganized Questionnaire'!G:G,"Very Complex")
A10: High executive-priority questions | B10: =COUNTIF('Reorganized Questionnaire'!D:D,"High")
A11: High LLM-error-risk questions | B11: =COUNTIF('Reorganized Questionnaire'!R:R,"High")
A14: Implementation principle
A15: • Simple questions: use FAQ Tool Call Binding and parameterized SQL; execute against live data.
A16: • Complex KPI questions: implement fixed formulas and joins in an Orbit KPI/Watchlist Tool. Do not let the LLM invent calculations.
A17: • Mesh can explain, compare, and narrate results only after the governed tool computes the metrics.
A18: • Questions depending on empty milestone, estimation, or team tables remain deferred until data is populated.

Sheet Reorganized Questionnaire
A1: Source | B1: Original ID | C1: Audience | D1: Executive Priority | E1: PMS Area | F1: Question Type | G1: Complexity Tag | H1: Canonical Intent | I1: Primary Question | J1: Alternative Phrasing 1 | K1: Alternative Phrasing 2 | L1: Required Parameters | M1: Business Decision / Value | N1: KPI / Derivation Logic | O1: Relevant Populated Tables | P1: Data Readiness | Q1: Query Strategy | R1: LLM Error Risk | S1: Recommended Execution / Cache | T1: Query Mapping Status | U1: SQL Query (Existing or Recovered) | V1: Notes
A2: Existing – Retained | B2: 1 | C2: Portfolio Head / Delivery Manager / PM | D2: Low | E2: Projects | F2: Simple Lookup / Filter | G2: Simple | H2: my_active_projects | I2: What are my active projects? | J2: Show the projects I am currently working on. | K2: List my ongoing projects. | L2: current_user | M2: Fast operational lookup and drill-down. | N2: Direct lookup/filter; no derived KPI. | O2: tbl_projects; tbl_project_users | P2: N/A | Q2: Parameterized lookup/filter | R2: Low | S2: FAQ Tool Call Binding + parameterized SQL; cache intent/SQL, not live response | T2: Not Mapped – Business Rule Required | U2: SELECT DISTINCT p.project_id, p.project_unique_id, p.project_key, p.title, p.start_date, p.end_date, ps.status_name, st.stage_name, p.priority, p.rag FROM tbl_projects p JOIN tbl_project_users pu ON p.project_id = pu.project_id LEFT JOIN tbl_project_status ps ON ps.status_id = p.project_status_id LEFT JOIN tbl_project_stages st ON st.stage_id = p.project_stage_id WHERE pu.user_id = 3066 AND pu.request_status = 'A' AND pu.status = 1 AND p.status = 1 AND p.archive = 0 ORDER BY p.title ASC | V2: Define whether “my” includes member, PM, owner, or task assignee.
A3: Existing – Retained | B3: 2 | C3: Portfolio Head / Delivery Manager / PM | D3: Low | E3: Projects | F3: Simple Lookup / Filter | G3: Simple | H3: projects_managed_by_me | I3: Which projects am I managing? | J3: Show projects where I am the project manager. | K3: List projects managed by me. | L3: current_user | M3: Fast operational lookup and drill-down. | N3: Direct lookup/filter; no derived KPI. | O3: tbl_projects.pm_user_id | P3: Data Available | Q3: Parameterized lookup/filter | R3: Low | S3: FAQ Tool Call Binding + parameterized SQL; cache intent/SQL, not live response | T3: Mapped – Direct Schema | U3: SELECT p.project_id, p.project_unique_id, p.project_key, p.title, p.start_date, p.end_date, ps.status_name, st.stage_name, p.priority, p.rag FROM tbl_projects p LEFT JOIN tbl_project_status ps ON ps.status_id = p.project_status_id LEFT JOIN tbl_project_stages st ON st.stage_id = p.project_stage_id WHERE p.pm_user_id = :current_user_id AND p.status = 1 AND p.archive = 0 ORDER BY p.end_date, p.title; | V3: Use PM field; confirm whether project_owner_id also counts.
A4: Existing – Retained | B4: 3 | C4: Portfolio Head / Delivery Manager / PM | D4: Low | E4: Projects | F4: Simple Lookup / Filter | G4: Simple | H4: projects_owned_by_me | I4: Which projects do I own? | J4: Show projects where I am the owner. | K4: List projects owned by me. | L4: current_user | M4: Fast operational lookup and drill-down. | N4: Direct lookup/filter; no derived KPI. | O4: tbl_projects.project_owner_id | P4: Data Available | Q4: Parameterized lookup/filter | R4: Low | S4: FAQ Tool Call Binding + parameterized SQL; cache intent/SQL, not live response | T4: Mapped – Direct Schema | U4: SELECT p.project_id, p.project_unique_id, p.project_key, p.title, p.start_date, p.end_date, ps.status_name, st.stage_name, p.priority, p.rag FROM tbl_projects p LEFT JOIN tbl_project_status ps ON ps.status_id = p.project_status_id LEFT JOIN tbl_project_stages st ON st.stage_id = p.project_stage_id WHERE p.project_owner_id = :current_user_id AND p.status = 1 AND p.archive = 0 ORDER BY p.end_date, p.title; | V4: Distinct from project manager.
A5: Existing – Retained | B5: 4 | C5: Portfolio Head / Delivery Manager / PM | D5: Medium | E5: Projects | F5: Simple Lookup / Filter | G5: Moderate | H5: project_details | I5: Show details of project :project_name. | J5: Give me the project information for :project_name. | K5: Open the summary of :project_name. | L5: project_name | M5: Fast operational lookup and drill-down. | N5: Direct lookup/filter; no derived KPI. | O5: tbl_projects | P5: N/A | Q5: Parameterized lookup/filter | R5: Medium | S5: FAQ/NL2SQL cached template or Orbit aggregation tool; execute on live data | T5: Not Mapped – Schema Ambiguous | V5: Project-name matching and duplicate-title handling required.
A6: Existing – Retained | B6: 5 | C6: Portfolio Head / Delivery Manager / PM | D6: Low | E6: Projects | F6: Simple Lookup / Filter | G6: Simple | H6: project_status | I6: What is the status of project :project_name? | J6: Show the current status of :project_name. | K6: Is :project_name active or completed? | L6: project_name | M6: Fast operational lookup and drill-down. | N6: Direct lookup/filter; no derived KPI. | O6: tbl_projects; tbl_project_status | P6: Data Available | Q6: Parameterized lookup/filter | R6: Low | S6: FAQ Tool Call Binding + parameterized SQL; cache intent/SQL, not live response | T6: Mapped – Direct Schema | U6: SELECT p.project_id, p.project_key, p.title, p.project_status_id, ps.status_name, ps.color_code FROM tbl_projects p LEFT JOIN tbl_project_status ps ON ps.status_id = p.project_status_id WHERE p.title = :project_name AND p.status = 1 AND p.archive = 0 ORDER BY p.project_id; | V6: Lookup master data required.
A7: Existing – Retained | B7: 6 | C7: Portfolio Head / Delivery Manager / PM | D7: Low | E7: Projects | F7: Simple Lookup / Filter | G7: Simple | H7: project_stage | I7: What stage is :project_name in? | J7: Show the current stage of :project_name. | K7: Which delivery stage has :project_name reached? | L7: project_name | M7: Fast operational lookup and drill-down. | N7: Direct lookup/filter; no derived KPI. | O7: tbl_projects; tbl_project_stages | P7: Data Available | Q7: Parameterized lookup/filter | R7: Low | S7: FAQ Tool Call Binding + parameterized SQL; cache intent/SQL, not live response | T7: Mapped – Direct Schema | U7: SELECT p.project_id, p.project_key, p.title, p.project_stage_id, st.stage_name, st.color_code FROM tbl_projects p LEFT JOIN tbl_project_stages st ON st.stage_id = p.project_stage_id WHERE p.title = :project_name AND p.status = 1 AND p.archive = 0 ORDER BY p.project_id; | V7: Lookup master data required.
A8: Existing – Retained | B8: 7 | C8: Portfolio Head / Delivery Manager / PM | D8: Low | E8: Projects | F8: Simple Lookup / Filter | G8: Simple | H8: project_rag | I8: What is the RAG status of :project_name? | J8: Show the health colour of :project_name. | K8: Is :project_name red, amber, or green? | L8: project_name | M8: Fast operational lookup and drill-down. | N8: Direct lookup/filter; no derived KPI. | O8: tbl_projects.rag | P8: Data Available | Q8: Parameterized lookup/filter | R8: Low | S8: FAQ Tool Call Binding + parameterized SQL; cache intent/SQL, not live response | T8: Mapped – Direct Schema | U8: SELECT p.project_id, p.project_key, p.title, p.rag FROM tbl_projects p WHERE p.title = :project_name AND p.status = 1 AND p.archive = 0 ORDER BY p.project_id; | V8: Confirm stored values and meaning.
A9: Existing – Reworked with Populated Alternative | B9: 8 | C9: Portfolio Head / Delivery Manager / PM | D9: Low | E9: Projects | F9: Simple Lookup / Filter | G9: Simple | H9: project_priority_code | I9: What priority code is stored for :project_name? | J9: Show the stored priority value for :project_name. | K9: What is the current project priority code for :project_name? | L9: project_name or project_unique_id | M9: Fast operational lookup and drill-down. | N9: Direct lookup/filter; no derived KPI. | O9: tbl_projects | P9: Available – Raw Code Only | Q9: Parameterized lookup/filter | R9: Low | S9: FAQ Tool Call Binding + parameterized SQL; cache intent/SQL, not live response | T9: Mapped – Populated Alternative | U9: SELECT p.project_id, p.project_unique_id, p.project_key, p.title, p.priority FROM tbl_projects p WHERE (p.project_unique_id = :project_identifier OR p.project_key = :project_identifier OR p.title = :project_identifier) AND p.status = 1 AND p.archive = 0 ORDER BY p.project_id; | V9: The lookup table tbl_project_priority is empty. The raw numeric value in tbl_projects.priority is available, but its business label must be confirmed. Recovered from empty-table dependency.
A10: Existing – Retained | B10: 9 | C10: Portfolio Head / Delivery Manager / PM | D10: Low | E10: Projects | F10: Simple Lookup / Filter | G10: Simple | H10: projects_starting_period | I10: Which projects start between :start_date and :end_date? | J10: Show projects beginning in the selected period. | K10: List upcoming project starts. | L10: start_date, end_date | M10: Fast operational lookup and drill-down. | N10: Direct lookup/filter; no derived KPI. | O10: tbl_projects.start_date | P10: Data Available | Q10: Parameterized lookup/filter | R10: Low | S10: FAQ Tool Call Binding + parameterized SQL; cache intent/SQL, not live response | T10: Mapped – Direct Schema | U10: SELECT p.project_id, p.project_key, p.title, p.start_date, p.end_date, ps.status_name, p.rag FROM tbl_projects p LEFT JOIN tbl_project_status ps ON ps.status_id = p.project_status_id WHERE p.start_date >= :start_date AND p.start_date < DATE_ADD(:end_date, INTERVAL 1 DAY) AND p.status = 1 AND p.archive = 0 ORDER BY p.start_date, p.title; | V10: Date boundaries to be inclusive.
A11: Existing – Retained | B11: 10 | C11: Portfolio Head / Delivery Manager / PM | D11: Low | E11: Projects | F11: Simple Lookup / Filter | G11: Simple | H11: projects_ending_period | I11: Which projects end between :start_date and :end_date? | J11: Show projects scheduled to finish in the selected period. | K11: List upcoming project end dates. | L11: start_date, end_date | M11: Fast operational lookup and drill-down. | N11: Direct lookup/filter; no derived KPI. | O11: tbl_projects.end_date | P11: Data Available | Q11: Parameterized lookup/filter | R11: Low | S11: FAQ Tool Call Binding + parameterized SQL; cache intent/SQL, not live response | T11: Mapped – Direct Schema | U11: SELECT p.project_id, p.project_key, p.title, p.start_date, p.end_date, ps.status_name, p.rag FROM tbl_projects p LEFT JOIN tbl_project_status ps ON ps.status_id = p.project_status_id WHERE p.end_date >= :start_date AND p.end_date < DATE_ADD(:end_date, INTERVAL 1 DAY) AND p.status = 1 AND p.archive = 0 ORDER BY p.end_date, p.title; | V11: Date boundaries to be inclusive.
A12: Existing – Retained | B12: 11 | C12: Portfolio Head / Delivery Manager / PM | D12: Medium | E12: Projects | F12: Exception / Diagnostic | G12: Complex | H12: overdue_projects | I12: Which projects are overdue? | J12: Show active projects past their end date. | K12: List delayed projects. | L12: as_of_date | M12: Identify exceptions requiring owner action. | N12: Define which project statuses are considered open. | O12: tbl_projects.end_date; tbl_project_status | P12: N/A | Q12: Exception query with joins and threshold filters | R12: High | S12: Orbit KPI Tool with predefined metric logic; Mesh may explain results but must not calculate metrics freely | T12: Not Applicable – Non-Direct Support | V12: Define which project statuses are considered open.
A13: Existing – Reworked with Populated Alternative | B13: 12 | C13: Portfolio Head / Delivery Manager / PM | D13: Low | E13: Projects | F13: Simple Lookup / Filter | G13: Simple | H13: projects_by_department | I13: Show active projects for department :department_name. | J13: Which active projects belong to :department_name? | K13: Give me the project portfolio for :department_name. | L13: department_name | M13: Fast operational lookup and drill-down. | N13: Direct lookup/filter; no derived KPI. | O13: tbl_projects; department | P13: Available – Alternative Table | Q13: Parameterized lookup/filter | R13: Low | S13: FAQ Tool Call Binding + parameterized SQL; cache intent/SQL, not live response | T13: Mapped – Populated Alternative | U13: SELECT p.project_id, p.project_unique_id, p.project_key, p.title, p.start_date, p.end_date, p.rag, d.name AS department_name FROM tbl_projects p JOIN department d ON d.group_id = p.department_id WHERE d.name = :department_name AND p.status = 1 AND p.archive = 0 ORDER BY p.end_date, p.title; | V13: Use populated department table instead of empty tbl_project_department. Confirm join tbl_projects.department_id = department.group_id. Recovered from empty-table dependency.
A14: Existing – Retained | B14: 14 | C14: Portfolio Head / Delivery Manager / PM | D14: Low | E14: Projects | F14: Simple Lookup / Filter | G14: Simple | H14: projects_by_type | I14: Show projects of type :project_type. | J14: List :project_type projects. | K14: Which projects use project type :project_type? | L14: project_type | M14: Fast operational lookup and drill-down. | N14: Direct lookup/filter; no derived KPI. | O14: tbl_projects.project_type_id; tbl_project_types | P14: Data Available | Q14: Parameterized lookup/filter | R14: Low | S14: FAQ Tool Call Binding + parameterized SQL; cache intent/SQL, not live response | T14: Mapped – Direct Schema | U14: SELECT p.project_id, p.project_key, p.title, pt.project_type, ps.status_name, p.start_date, p.end_date FROM tbl_projects p JOIN tbl_project_types pt ON pt.project_type_id = p.project_type_id LEFT JOIN tbl_project_status ps ON ps.status_id = p.project_status_id WHERE pt.project_type = :project_type AND p.status = 1 AND p.archive = 0 ORDER BY p.title; | V14: Lookup values required.
A15: Existing – Retained | B15: 15 | C15: Portfolio Head / Delivery Manager / PM | D15: Medium | E15: Projects | F15: Derived Analysis | G15: Very Complex | H15: projects_by_client | I15: Show projects for client :client_name. | J15: List projects associated with :client_name. | K15: Which projects belong to :client_name? | L15: client_name | M15: Support governed management analysis. | N15: Client master table must be confirmed. | O15: tbl_projects.client_id | P15: N/A | Q15: Governed multi-table query | R15: High | S15: Orbit KPI Tool with predefined metric logic; Mesh may explain results but must not calculate metrics freely | T15: Not Applicable – Non-Direct Support | V15: Client master table must be confirmed.
A16: Existing – Retained | B16: 16 | C16: Portfolio Head / Delivery Manager / PM | D16: High | E16: Projects | F16: Aggregation / Dashboard KPI | G16: Complex | H16: project_team_size | I16: How many active users are allocated to :project_name? | J16: Show the team size of :project_name. | K16: How many people are on :project_name? | L16: project_name | M16: Provide a reusable dashboard metric for monitoring. | N16: Define active allocation and request_status filters. | O16: tbl_project_users | P16: N/A | Q16: Predefined aggregation / grouped KPI query | R16: High | S16: Orbit KPI Tool with predefined metric logic; Mesh may explain results but must not calculate metrics freely | T16: Not Mapped – Business Rule Required | V16: Define active allocation and request_status filters.
A17: Existing – Retained | B17: 17 | C17: Portfolio Head / Delivery Manager / PM | D17: Medium | E17: Projects | F17: Exception / Diagnostic | G17: Moderate | H17: projects_without_pm | I17: Which projects do not have a project manager? | J17: Show projects with no PM assigned. | K17: List unowned PM assignments. | L17: none | M17: Identify exceptions requiring owner action. | N17: Null and zero handling required. | O17: tbl_projects.pm_user_id | P17: Data Available | Q17: Exception query with joins and threshold filters | R17: Medium | S17: FAQ/NL2SQL cached template or Orbit aggregation tool; execute on live data | T17: Mapped – Direct Schema | U17: SELECT p.project_id, p.project_key, p.title, p.start_date, p.end_date, ps.status_name FROM tbl_projects p LEFT JOIN tbl_project_status ps ON ps.status_id = p.project_status_id WHERE p.pm_user_id IS NULL AND p.status = 1 AND p.archive = 0 ORDER BY p.title; | V17: Null and zero handling required.
A18: Existing – Retained | B18: 18 | C18: Portfolio Head / Delivery Manager / PM | D18: Medium | E18: Projects | F18: Exception / Diagnostic | G18: Complex | H18: projects_without_members | I18: Which active projects have no allocated users? | J18: Show projects without team members. | K18: List active projects with an empty team. | L18: none | M18: Identify exceptions requiring owner action. | N18: Define active project and active membership. | O18: tbl_projects; tbl_project_users | P18: N/A | Q18: Exception query with joins and threshold filters | R18: High | S18: Orbit KPI Tool with predefined metric logic; Mesh may explain results but must not calculate metrics freely | T18: Not Applicable – Non-Direct Support | V18: Define active project and active membership.
A19: Existing – Reworked with Populated Alternative | B19: 19 | C19: Portfolio Head / Delivery Manager / PM | D19: Medium | E19: Projects | F19: Derived Analysis | G19: Very Complex | H19: project_recent_activity | I19: What project records were updated recently for :project_name? | J19: Show recent project, task, issue, and risk activity for :project_name. | K19: What activity has occurred on :project_name in the last :days days? | L19: project_identifier; days | M19: Support governed management analysis. | N19: The empty project status history table cannot provide an exact status-change log. This replacement provides a recent activity feed from populated update timestamps and risk history. | O19: tbl_projects; tbl_project_tasks; tbl_project_issues; tbl_risk; tbl_risk_history | P19: Available – Reframed Activity View | Q19: Governed multi-table query | R19: High | S19: Orbit KPI Tool with predefined metric logic; Mesh may explain results but must not calculate metrics freely | T19: Pending – Multi-source Activity Query | V19: The empty project status history table cannot provide an exact status-change log. This replacement provides a recent activity feed from populated update timestamps and risk history. Recovered from empty-table dependency.
A20: Existing – Retained | B20: 20 | C20: CEO / Executive / Portfolio Head | D20: High | E20: Projects | F20: Aggregation / Dashboard KPI | G20: Complex | H20: active_project_portfolio | I20: Give me a summary of active projects. | J20: Show active project counts by status and stage. | K20: Summarize the current project portfolio. | L20: current_user_scope | M20: Provide a reusable dashboard metric for monitoring. | N20: Define visibility scope and summary measures. | O20: tbl_projects; status/stage masters | P20: N/A | Q20: Predefined aggregation / grouped KPI query | R20: High | S20: Orbit KPI Tool with predefined metric logic; Mesh may explain results but must not calculate metrics freely | T20: Not Applicable – Non-Direct Support | V20: Define visibility scope and summary measures.
A21: Existing – Retained | B21: 26 | C21: Portfolio Head / Delivery Manager / PM | D21: Medium | E21: Milestones | F21: Derived Analysis | G21: Complex | H21: milestone_task_progress | I21: What is the task completion progress of milestone :milestone_name? | J21: How many milestone tasks are completed? | K21: Show completed versus open tasks for :milestone_name. | L21: milestone_name, project_name | M21: Support governed management analysis. | N21: Define closed task statuses. | O21: mapping; tasks; task status | P21: N/A | Q21: Governed multi-table query | R21: High | S21: Orbit KPI Tool with predefined metric logic; Mesh may explain results but must not calculate metrics freely | T21: Not Applicable – Non-Direct Support | V21: Define closed task statuses.
A22: Existing – Retained | B22: 28 | C22: Portfolio Head / Delivery Manager / PM | D22: Medium | E22: Milestones | F22: Derived Analysis | G22: Complex | H22: milestone_date_slippage | I22: Which milestone dates differ from their mapped task dates? | J22: Show milestones with task schedules outside milestone dates. | K22: List milestone schedule mismatches. | L22: none | M22: Support governed management analysis. | N22: No baseline milestone date exists; this is schedule consistency, not baseline slippage. | O22: milestone tables; mapping | P22: N/A | Q22: Governed multi-table query | R22: High | S22: Orbit KPI Tool with predefined metric logic; Mesh may explain results but must not calculate metrics freely | T22: Not Applicable – Non-Direct Support | V22: No baseline milestone date exists; this is schedule consistency, not baseline slippage.
A23: Existing – Retained | B23: 30 | C23: Portfolio Head / Delivery Manager / PM | D23: Medium | E23: Milestones | F23: Derived Analysis | G23: Very Complex | H23: milestone_owner | I23: Who owns milestone :milestone_name? | J23: Show the owner of :milestone_name. | K23: Who is responsible for :milestone_name? | L23: milestone_name | M23: Support governed management analysis. | N23: No owner column exists on milestone table; may be inferred from task owners only. | O23: milestone tables | P23: N/A | Q23: Governed multi-table query | R23: High | S23: Orbit KPI Tool with predefined metric logic; Mesh may explain results but must not calculate metrics freely | T23: Not Applicable – Non-Direct Support | V23: No owner column exists on milestone table; may be inferred from task owners only.
A24: Existing – Retained | B24: 31 | C24: PM / Team Lead / Employee | D24: Medium | E24: Tasks | F24: Simple Lookup / Filter | G24: Moderate | H24: my_open_tasks | I24: What are my open tasks? | J24: Show tasks assigned to me that are not closed. | K24: List my pending work items. | L24: current_user | M24: Fast operational lookup and drill-down. | N24: Direct lookup/filter; no derived KPI. | O24: tbl_project_task_users; tbl_project_tasks; task status | P24: N/A | Q24: Parameterized lookup/filter | R24: Medium | S24: FAQ/NL2SQL cached template or Orbit aggregation tool; execute on live data | T24: Not Mapped – Business Rule Required | V24: Define open status types and whether task_owner also counts.
A25: Existing – Retained | B25: 32 | C25: PM / Team Lead / Employee | D25: Low | E25: Tasks | F25: Simple Lookup / Filter | G25: Simple | H25: my_tasks_due_today | I25: Which of my tasks are due today? | J25: Show my tasks with today’s due date. | K25: What work is due for me today? | L25: current_user, current_date | M25: Fast operational lookup and drill-down. | N25: Direct lookup/filter; no derived KPI. | O25: task users; tasks | P25: Data Available | Q25: Parameterized lookup/filter | R25: Low | S25: FAQ Tool Call Binding + parameterized SQL; cache intent/SQL, not live response | T25: Mapped – Direct Schema | U25: SELECT t.task_id, t.reference_no, t.title, p.title AS project_title, t.due_date, ts.status_name, t.priority, t.rag, t.percent_complete FROM tbl_project_task_users tu JOIN tbl_project_tasks t ON t.task_id = tu.task_id JOIN tbl_projects p ON p.project_id = t.project_id LEFT JOIN tbl_project_task_status ts ON ts.task_status_id = t.task_status_id WHERE tu.user_id = :current_user_id AND tu.status = 1 AND t.status = 1 AND t.archive = 0 AND DATE(t.due_date) = CURRENT_DATE ORDER BY t.due_date, t.reference_no; | V25: Use organization timezone.
A26: Existing – Retained | B26: 33 | C26: PM / Team Lead / Employee | D26: Medium | E26: Tasks | F26: Exception / Diagnostic | G26: Complex | H26: my_overdue_tasks | I26: Which of my tasks are overdue? | J26: Show my delayed tasks. | K26: List my open tasks past their due date. | L26: current_user, as_of_date | M26: Identify exceptions requiring owner action. | N26: Define open statuses. | O26: task users; tasks; task status | P26: N/A | Q26: Exception query with joins and threshold filters | R26: High | S26: Orbit KPI Tool with predefined metric logic; Mesh may explain results but must not calculate metrics freely | T26: Not Applicable – Non-Direct Support | V26: Define open statuses.
A27: Existing – Retained | B27: 34 | C27: PM / Team Lead / Employee | D27: Low | E27: Tasks | F27: Simple Lookup / Filter | G27: Simple | H27: tasks_assigned_to_user | I27: Show tasks assigned to :employee_name. | J27: List :employee_name’s tasks. | K27: What work is assigned to :employee_name? | L27: employee_name | M27: Fast operational lookup and drill-down. | N27: Direct lookup/filter; no derived KPI. | O27: tbl_project_task_users; tbl_users; tasks | P27: Data Available | Q27: Parameterized lookup/filter | R27: Low | S27: FAQ Tool Call Binding + parameterized SQL; cache intent/SQL, not live response | T27: Mapped – Direct Schema | U27: SELECT u.user_id, CONCAT_WS(' ', u.first_name, u.last_name) AS employee_name, p.title AS project_title, t.task_id, t.reference_no, t.title AS task_title, t.due_date, ts.status_name, tu.allot_percentage FROM tbl_users u JOIN tbl_project_task_users tu ON tu.user_id = u.user_id JOIN tbl_project_tasks t ON t.task_id = tu.task_id JOIN tbl_projects p ON p.project_id = t.project_id LEFT JOIN tbl_project_task_status ts ON ts.task_status_id = t.task_status_id WHERE CONCAT_WS(' ', u.first_name, u.last_name) = :employee_name AND tu.status = 1 AND t.status = 1 AND t.archive = 0 ORDER BY p.title, t.due_date, t.reference_no; | V27: Handle active assignment status.
A28: Existing – Retained | B28: 35 | C28: PM / Team Lead / Employee | D28: Medium | E28: Tasks | F28: Derived Analysis | G28: Complex | H28: project_open_tasks | I28: Show open tasks for :project_name. | J28: List pending tasks under :project_name. | K28: What work remains for :project_name? | L28: project_name | M28: Support governed management analysis. | N28: Define open statuses. | O28: tasks; task status | P28: N/A | Q28: Governed multi-table query | R28: High | S28: Orbit KPI Tool with predefined metric logic; Mesh may explain results but must not calculate metrics freely | T28: Not Applicable – Non-Direct Support | V28: Define open statuses.
A29: Existing – Retained | B29: 36 | C29: PM / Team Lead / Employee | D29: Medium | E29: Tasks | F29: Derived Analysis | G29: Complex | H29: project_closed_tasks | I29: Show completed tasks for :project_name. | J29: List closed tasks under :project_name. | K29: What tasks are finished in :project_name? | L29: project_name | M29: Support governed management analysis. | N29: Define closed status types. | O29: tasks; task status | P29: N/A | Q29: Governed multi-table query | R29: High | S29: Orbit KPI Tool with predefined metric logic; Mesh may explain results but must not calculate metrics freely | T29: Not Applicable – Non-Direct Support | V29: Define closed status types.
A30: Existing – Retained | B30: 37 | C30: PM / Team Lead / Employee | D30: Medium | E30: Tasks | F30: Exception / Diagnostic | G30: Complex | H30: unassigned_tasks | I30: Which tasks are unassigned? | J30: Show tasks with no active assignee. | K30: List unallocated tasks. | L30: project_scope | M30: Identify exceptions requiring owner action. | N30: Confirm whether task_owner is an assignment. | O30: tasks; task users | P30: N/A | Q30: Exception query with joins and threshold filters | R30: High | S30: Orbit KPI Tool with predefined metric logic; Mesh may explain results but must not calculate metrics freely | T30: Not Applicable – Non-Direct Support | V30: Confirm whether task_owner is an assignment.
A31: Existing – Retained | B31: 38 | C31: PM / Team Lead / Employee | D31: Medium | E31: Tasks | F31: Derived Analysis | G31: Complex | H31: high_priority_tasks | I31: Show high-priority open tasks. | J31: List urgent pending tasks. | K31: Which open tasks have high priority? | L31: project_scope | M31: Support governed management analysis. | N31: Confirm priority values. | O31: tasks.priority; task status | P31: N/A | Q31: Governed multi-table query | R31: High | S31: Orbit KPI Tool with predefined metric logic; Mesh may explain results but must not calculate metrics freely | T31: Not Applicable – Non-Direct Support | V31: Confirm priority values.
A32: Existing – Retained | B32: 39 | C32: PM / Team Lead / Employee | D32: Low | E32: Tasks | F32: Simple Lookup / Filter | G32: Simple | H32: red_rag_tasks | I32: Which tasks have a red RAG status? | J32: Show red-health tasks. | K32: List tasks flagged red. | L32: project_scope | M32: Fast operational lookup and drill-down. | N32: Direct lookup/filter; no derived KPI. | O32: tbl_project_tasks.rag | P32: Data Available | Q32: Parameterized lookup/filter | R32: Low | S32: FAQ Tool Call Binding + parameterized SQL; cache intent/SQL, not live response | T32: Mapped – Direct Schema | U32: SELECT t.task_id, t.reference_no, t.title, p.title AS project_title, t.rag, t.due_date, ts.status_name FROM tbl_project_tasks t JOIN tbl_projects p ON p.project_id = t.project_id LEFT JOIN tbl_project_task_status ts ON ts.task_status_id = t.task_status_id WHERE LOWER(t.rag) = 'red' AND t.status = 1 AND t.archive = 0 ORDER BY t.due_date, p.title; | V32: Confirm stored RAG values.
A33: Existing – Retained | B33: 40 | C33: PM / Team Lead / Employee | D33: Low | E33: Tasks | F33: Simple Lookup / Filter | G33: Simple | H33: tasks_due_period | I33: Which tasks are due between :start_date and :end_date? | J33: Show tasks due in the selected period. | K33: List upcoming task deadlines. | L33: start_date, end_date | M33: Fast operational lookup and drill-down. | N33: Direct lookup/filter; no derived KPI. | O33: tbl_project_tasks.due_date | P33: Data Available | Q33: Parameterized lookup/filter | R33: Low | S33: FAQ Tool Call Binding + parameterized SQL; cache intent/SQL, not live response | T33: Mapped – Direct Schema | U33: SELECT t.task_id, t.reference_no, t.title, p.title AS project_title, t.due_date, ts.status_name, t.priority, t.rag FROM tbl_project_tasks t JOIN tbl_projects p ON p.project_id = t.project_id LEFT JOIN tbl_project_task_status ts ON ts.task_status_id = t.task_status_id WHERE t.due_date >= :start_date AND t.due_date < DATE_ADD(:end_date, INTERVAL 1 DAY) AND t.status = 1 AND t.archive = 0 ORDER BY t.due_date, p.title, t.reference_no; | V33: Default visibility scope required.
A34: Existing – Retained | B34: 41 | C34: PM / Team Lead / Employee | D34: Low | E34: Tasks | F34: Simple Lookup / Filter | G34: Simple | H34: task_details | I34: Show details of task :task_reference. | J34: Give me the task summary for :task_reference. | K34: Open task :task_reference. | L34: task_reference | M34: Fast operational lookup and drill-down. | N34: Direct lookup/filter; no derived KPI. | O34: tbl_project_tasks | P34: Data Available | Q34: Parameterized lookup/filter | R34: Low | S34: FAQ Tool Call Binding + parameterized SQL; cache intent/SQL, not live response | T34: Mapped – Direct Schema | U34: SELECT t.task_id, t.reference_no, t.title, t.description, p.project_id, p.title AS project_title, t.task_owner, t.start_date, t.due_date, t.task_status_id, ts.status_name, t.priority, t.rag, t.estimate, t.actual_hours, t.percent_complete, t.update_date FROM tbl_project_tasks t JOIN tbl_projects p ON p.project_id = t.project_id LEFT JOIN tbl_project_task_status ts ON ts.task_status_id = t.task_status_id WHERE t.reference_no = :task_reference AND t.status = 1 AND t.archive = 0; | V34: Prefer reference_no over title.
A35: Existing – Retained | B35: 42 | C35: PM / Team Lead / Employee | D35: Low | E35: Tasks | F35: Simple Lookup / Filter | G35: Simple | H35: subtasks_of_task | I35: Show subtasks of :task_reference. | J35: List child tasks under :task_reference. | K35: What tasks depend hierarchically on :task_reference? | L35: task_reference | M35: Fast operational lookup and drill-down. | N35: Direct lookup/filter; no derived KPI. | O35: tbl_project_tasks.parent_id | P35: Data Available | Q35: Parameterized lookup/filter | R35: Low | S35: FAQ Tool Call Binding + parameterized SQL; cache intent/SQL, not live response | T35: Mapped – Direct Schema | U35: SELECT c.task_id, c.reference_no, c.title, c.start_date, c.due_date, ts.status_name, c.priority, c.rag, c.percent_complete FROM tbl_project_tasks parent JOIN tbl_project_tasks c ON c.parent_id = parent.task_id LEFT JOIN tbl_project_task_status ts ON ts.task_status_id = c.task_status_id WHERE parent.reference_no = :task_reference AND c.status = 1 AND c.archive = 0 ORDER BY c.due_date, c.reference_no; | V35: Hierarchy only; not dependency semantics.
A36: Existing – Retained | B36: 43 | C36: PM / Team Lead / Employee | D36: Low | E36: Tasks | F36: Simple Lookup / Filter | G36: Simple | H36: task_assignees | I36: Who is assigned to task :task_reference? | J36: Show all assignees for :task_reference. | K36: Which users are allocated to :task_reference? | L36: task_reference | M36: Fast operational lookup and drill-down. | N36: Direct lookup/filter; no derived KPI. | O36: tbl_project_task_users; tbl_users | P36: Data Available | Q36: Parameterized lookup/filter | R36: Low | S36: FAQ Tool Call Binding + parameterized SQL; cache intent/SQL, not live response | T36: Mapped – Direct Schema | U36: SELECT u.user_id, CONCAT_WS(' ', u.first_name, u.last_name) AS employee_name, u.email, tu.allot_percentage, tu.post_date AS assigned_on FROM tbl_project_tasks t JOIN tbl_project_task_users tu ON tu.task_id = t.task_id JOIN tbl_users u ON u.user_id = tu.user_id WHERE t.reference_no = :task_reference AND tu.status = 1 ORDER BY employee_name; | V36: Include allot_percentage.
A37: Existing – Retained | B37: 44 | C37: PM / Team Lead / Employee | D37: Low | E37: Tasks | F37: Simple Lookup / Filter | G37: Simple | H37: task_allocation_percentages | I37: Show allocation percentages for task :task_reference. | J37: How is task :task_reference allocated? | K37: List assignees and percentages for :task_reference. | L37: task_reference | M37: Fast operational lookup and drill-down. | N37: Direct lookup/filter; no derived KPI. | O37: tbl_project_task_users.allot_percentage | P37: Data Available | Q37: Parameterized lookup/filter | R37: Low | S37: FAQ Tool Call Binding + parameterized SQL; cache intent/SQL, not live response | T37: Mapped – Direct Schema | U37: SELECT u.user_id, CONCAT_WS(' ', u.first_name, u.last_name) AS employee_name, tu.allot_percentage FROM tbl_project_tasks t JOIN tbl_project_task_users tu ON tu.task_id = t.task_id JOIN tbl_users u ON u.user_id = tu.user_id WHERE t.reference_no = :task_reference AND tu.status = 1 ORDER BY tu.allot_percentage DESC, employee_name; | V37: Confirm whether total may exceed 100%.
A38: Existing – Retained | B38: 45 | C38: PM / Team Lead / Employee | D38: Medium | E38: Tasks | F38: Exception / Diagnostic | G38: Complex | H38: tasks_without_due_date | I38: Which open tasks have no due date? | J38: Show pending tasks missing deadlines. | K38: List tasks without a due date. | L38: project_scope | M38: Identify exceptions requiring owner action. | N38: Define open statuses. | O38: tasks; task status | P38: N/A | Q38: Exception query with joins and threshold filters | R38: High | S38: Orbit KPI Tool with predefined metric logic; Mesh may explain results but must not calculate metrics freely | T38: Not Applicable – Non-Direct Support | V38: Define open statuses.
A39: Existing – Retained | B39: 46 | C39: PM / Team Lead / Employee | D39: Low | E39: Tasks | F39: Simple Lookup / Filter | G39: Simple | H39: task_progress | I39: What is the completion percentage of task :task_reference? | J39: Show progress for :task_reference. | K39: How complete is :task_reference? | L39: task_reference | M39: Fast operational lookup and drill-down. | N39: Direct lookup/filter; no derived KPI. | O39: tbl_project_tasks.percent_complete | P39: Data Available | Q39: Parameterized lookup/filter | R39: Low | S39: FAQ Tool Call Binding + parameterized SQL; cache intent/SQL, not live response | T39: Mapped – Direct Schema | U39: SELECT t.task_id, t.reference_no, t.title, t.percent_complete, ts.status_name, t.update_date FROM tbl_project_tasks t LEFT JOIN tbl_project_task_status ts ON ts.task_status_id = t.task_status_id WHERE t.reference_no = :task_reference AND t.status = 1 AND t.archive = 0; | V39: Validate scale 0–100.
A40: Existing – Retained | B40: 47 | C40: PM / Team Lead / Employee | D40: Medium | E40: Tasks | F40: KPI / Comparative | G40: Complex | H40: task_estimate_vs_actual | I40: Compare estimate and actual hours for task :task_reference. | J40: Show planned versus actual effort for :task_reference. | K40: Is :task_reference over its estimate? | L40: task_reference | M40: Support prioritisation and performance comparison. | N40: Confirm units. | O40: tbl_project_tasks.estimate; actual_hours | P40: Data Available | Q40: Multi-table derived KPI with controlled formula | R40: High | S40: Orbit KPI Tool with predefined metric logic; Mesh may explain results but must not calculate metrics freely | T40: Mapped – Direct Schema | U40: SELECT t.task_id, t.reference_no, t.title, t.estimate AS estimated_hours, t.actual_hours, (t.actual_hours - t.estimate) AS variance_hours, t.estimate_complete AS remaining_estimate_hours FROM tbl_project_tasks t WHERE t.reference_no = :task_reference AND t.status = 1 AND t.archive = 0; | V40: Confirm units.
A41: Existing – Retained | B41: 48 | C41: PM / Team Lead / Employee | D41: Medium | E41: Tasks | F41: Exception / Diagnostic | G41: Complex | H41: tasks_over_estimate | I41: Which tasks have exceeded their estimated hours? | J41: Show tasks where actual hours are above estimate. | K41: List effort-overrun tasks. | L41: project_scope | M41: Identify exceptions requiring owner action. | N41: Null/zero estimate handling. | O41: tbl_project_tasks.estimate; actual_hours | P41: N/A | Q41: Exception query with joins and threshold filters | R41: High | S41: Orbit KPI Tool with predefined metric logic; Mesh may explain results but must not calculate metrics freely | T41: Not Applicable – Non-Direct Support | V41: Null/zero estimate handling.
A42: Existing – Retained | B42: 49 | C42: PM / Team Lead / Employee | D42: Low | E42: Tasks | F42: Simple Lookup / Filter | G42: Simple | H42: recently_updated_tasks | I42: Which tasks were updated in the last :days days? | J42: Show recently changed tasks. | K42: List tasks updated recently. | L42: days | M42: Fast operational lookup and drill-down. | N42: Direct lookup/filter; no derived KPI. | O42: tbl_project_tasks.update_date | P42: Data Available | Q42: Parameterized lookup/filter | R42: Low | S42: FAQ Tool Call Binding + parameterized SQL; cache intent/SQL, not live response | T42: Mapped – Direct Schema | U42: SELECT t.task_id, t.reference_no, t.title, p.title AS project_title, t.update_date, ts.status_name, t.percent_complete FROM tbl_project_tasks t JOIN tbl_projects p ON p.project_id = t.project_id LEFT JOIN tbl_project_task_status ts ON ts.task_status_id = t.task_status_id WHERE t.update_date >= DATE_SUB(NOW(), INTERVAL :days DAY) AND t.status = 1 AND t.archive = 0 ORDER BY t.update_date DESC; | V42: Visibility scope required.
A43: Existing – Retained | B43: 50 | C43: PM / Team Lead / Employee | D43: Medium | E43: Tasks | F43: Exception / Diagnostic | G43: Complex | H43: stale_open_tasks | I43: Which open tasks have not been updated in :days days? | J43: Show stale pending tasks. | K43: List inactive open tasks. | L43: days | M43: Identify exceptions requiring owner action. | N43: Define open statuses. | O43: tasks; task status | P43: N/A | Q43: Exception query with joins and threshold filters | R43: High | S43: Orbit KPI Tool with predefined metric logic; Mesh may explain results but must not calculate metrics freely | T43: Not Applicable – Non-Direct Support | V43: Define open statuses.
A44: Existing – Retained | B44: 51 | C44: PM / Team Lead / Employee | D44: High | E44: Tasks | F44: Aggregation / Dashboard KPI | G44: Moderate | H44: task_status_counts | I44: Show task counts by status for :project_name. | J44: Summarize tasks by workflow status for :project_name. | K44: How many tasks are in each status for :project_name? | L44: project_name | M44: Provide a reusable dashboard metric for monitoring. | N44: Lookup data required. | O44: tasks; task status | P44: Data Available | Q44: Predefined aggregation / grouped KPI query | R44: Medium | S44: FAQ/NL2SQL cached template or Orbit aggregation tool; execute on live data | T44: Mapped – Direct Schema | U44: SELECT ts.task_status_id, ts.status_name, ts.status_type, COUNT(*) AS task_count FROM tbl_project_tasks t JOIN tbl_projects p ON p.project_id = t.project_id LEFT JOIN tbl_project_task_status ts ON ts.task_status_id = t.task_status_id WHERE p.title = :project_name AND t.status = 1 AND t.archive = 0 GROUP BY ts.task_status_id, ts.status_name, ts.status_type ORDER BY ts.status_order, ts.status_name; | V44: Lookup data required.
A45: Existing – Retained | B45: 52 | C45: PM / Team Lead / Employee | D45: High | E45: Tasks | F45: Aggregation / Dashboard KPI | G45: Complex | H45: task_workload_by_user | I45: Show task workload by user for :project_name. | J45: How many tasks does each person have on :project_name? | K45: Summarize assigned tasks by team member. | L45: project_name | M45: Provide a reusable dashboard metric for monitoring. | N45: Define whether workload means count, estimate, or allocation percentage. | O45: tasks; task users; users | P45: N/A | Q45: Predefined aggregation / grouped KPI query | R45: High | S45: Orbit KPI Tool with predefined metric logic; Mesh may explain results but must not calculate metrics freely | T45: Not Applicable – Non-Direct Support | V45: Define whether workload means count, estimate, or allocation percentage.
A46: Existing – Retained | B46: 53 | C46: Delivery Head / Resource Manager / PM | D46: High | E46: Timesheets | F46: Aggregation / Dashboard KPI | G46: Moderate | H46: my_logged_hours_today | I46: How many hours did I log today? | J46: Show my time entries for today. | K46: What is my total logged time today? | L46: current_user, current_date | M46: Provide a reusable dashboard metric for monitoring. | N46: Combine hours and minutes. | O46: tbl_timesheets | P46: Data Available | Q46: Predefined aggregation / grouped KPI query | R46: Medium | S46: FAQ/NL2SQL cached template or Orbit aggregation tool; execute on live data | T46: Mapped – Direct Schema | U46: SELECT ts.user_id, ts.timesheet_date, SUM(ts.hours * 60 + ts.minutes) / 60.0 AS total_hours FROM tbl_timesheets ts WHERE ts.user_id = :current_user_id AND ts.timesheet_date = CURRENT_DATE GROUP BY ts.user_id, ts.timesheet_date; | V46: Combine hours and minutes.
A47: Existing – Retained | B47: 54 | C47: Delivery Head / Resource Manager / PM | D47: High | E47: Timesheets | F47: Aggregation / Dashboard KPI | G47: Moderate | H47: my_logged_hours_period | I47: How many hours did I log between :start_date and :end_date? | J47: Show my logged time for the selected period. | K47: Total my timesheet hours for the period. | L47: current_user, start_date, end_date | M47: Provide a reusable dashboard metric for monitoring. | N47: Combine hours and minutes. | O47: tbl_timesheets | P47: Data Available | Q47: Predefined aggregation / grouped KPI query | R47: Medium | S47: FAQ/NL2SQL cached template or Orbit aggregation tool; execute on live data | T47: Mapped – Direct Schema | U47: SELECT ts.user_id, SUM(ts.hours * 60 + ts.minutes) / 60.0 AS total_hours FROM tbl_timesheets ts WHERE ts.user_id = :current_user_id AND ts.timesheet_date BETWEEN :start_date AND :end_date GROUP BY ts.user_id; | V47: Combine hours and minutes.
A48: Existing – Retained | B48: 55 | C48: Delivery Head / Resource Manager / PM | D48: Low | E48: Timesheets | F48: Simple Lookup / Filter | G48: Simple | H48: employee_logged_hours | I48: Show hours logged by :employee_name between :start_date and :end_date. | J48: How much time did :employee_name record? | K48: List :employee_name’s timesheet total. | L48: employee_name, start_date, end_date | M48: Fast operational lookup and drill-down. | N48: Direct lookup/filter; no derived KPI. | O48: tbl_timesheets; tbl_users | P48: Data Available | Q48: Parameterized lookup/filter | R48: Low | S48: FAQ Tool Call Binding + parameterized SQL; cache intent/SQL, not live response | T48: Mapped – Direct Schema | U48: SELECT u.user_id, CONCAT_WS(' ', u.first_name, u.last_name) AS employee_name, SUM(ts.hours * 60 + ts.minutes) / 60.0 AS total_hours FROM tbl_users u JOIN tbl_timesheets ts ON ts.user_id = u.user_id WHERE CONCAT_WS(' ', u.first_name, u.last_name) = :employee_name AND ts.timesheet_date BETWEEN :start_date AND :end_date GROUP BY u.user_id, u.first_name, u.last_name; | V48: RBAC needed for manager access.
A49: Existing – Retained | B49: 56 | C49: Delivery Head / Resource Manager / PM | D49: High | E49: Timesheets | F49: Aggregation / Dashboard KPI | G49: Moderate | H49: project_logged_hours | I49: How many hours were logged on :project_name between :start_date and :end_date? | J49: Show total project time for the period. | K49: What is the booked effort on :project_name? | L49: project_name, start_date, end_date | M49: Provide a reusable dashboard metric for monitoring. | N49: Timesheet links to project through task. | O49: tbl_timesheets; tasks; projects | P49: Data Available | Q49: Predefined aggregation / grouped KPI query | R49: Medium | S49: FAQ/NL2SQL cached template or Orbit aggregation tool; execute on live data | T49: Mapped – Direct Schema | U49: SELECT p.project_id, p.title AS project_title, SUM(ts.hours * 60 + ts.minutes) / 60.0 AS total_hours FROM tbl_timesheets ts JOIN tbl_project_tasks t ON t.task_id = ts.task_id JOIN tbl_projects p ON p.project_id = t.project_id WHERE p.title = :project_name AND ts.timesheet_date BETWEEN :start_date AND :end_date GROUP BY p.project_id, p.title; | V49: Timesheet links to project through task.
A50: Existing – Retained | B50: 57 | C50: Delivery Head / Resource Manager / PM | D50: Low | E50: Timesheets | F50: Simple Lookup / Filter | G50: Simple | H50: project_hours_by_user | I50: Show hours by user for :project_name. | J50: Who logged how much time on :project_name? | K50: Break down project hours by team member. | L50: project_name, start_date, end_date | M50: Fast operational lookup and drill-down. | N50: Direct lookup/filter; no derived KPI. | O50: timesheets; tasks; users | P50: Data Available | Q50: Parameterized lookup/filter | R50: Low | S50: FAQ Tool Call Binding + parameterized SQL; cache intent/SQL, not live response | T50: Mapped – Direct Schema | U50: SELECT u.user_id, CONCAT_WS(' ', u.first_name, u.last_name) AS employee_name, SUM(ts.hours * 60 + ts.minutes) / 60.0 AS total_hours FROM tbl_timesheets ts JOIN tbl_project_tasks t ON t.task_id = ts.task_id JOIN tbl_projects p ON p.project_id = t.project_id JOIN tbl_users u ON u.user_id = ts.user_id WHERE p.title = :project_name AND ts.timesheet_date BETWEEN :start_date AND :end_date GROUP BY u.user_id, u.first_name, u.last_name ORDER BY total_hours DESC; | V50: Date period should be mandatory or defaulted.
A51: Existing – Retained | B51: 58 | C51: Delivery Head / Resource Manager / PM | D51: High | E51: Timesheets | F51: Aggregation / Dashboard KPI | G51: Moderate | H51: hours_by_task | I51: How many hours were logged against task :task_reference? | J51: Show booked time for :task_reference. | K51: What is the total effort recorded on :task_reference? | L51: task_reference, start_date, end_date | M51: Provide a reusable dashboard metric for monitoring. | N51: Combine hours and minutes. | O51: tbl_timesheets; tasks | P51: Data Available | Q51: Predefined aggregation / grouped KPI query | R51: Medium | S51: FAQ/NL2SQL cached template or Orbit aggregation tool; execute on live data | T51: Mapped – Direct Schema | U51: SELECT t.task_id, t.reference_no, t.title, SUM(ts.hours * 60 + ts.minutes) / 60.0 AS total_hours FROM tbl_project_tasks t LEFT JOIN tbl_timesheets ts ON ts.task_id = t.task_id WHERE t.reference_no = :task_reference GROUP BY t.task_id, t.reference_no, t.title; | V51: Combine hours and minutes.
A52: Existing – Retained | B52: 59 | C52: Delivery Head / Resource Manager / PM | D52: Medium | E52: Timesheets | F52: Derived Analysis | G52: Very Complex | H52: timesheet_entries_by_task_type | I52: Show logged hours by project task type. | J52: Break down timesheet hours by task type. | K52: How much time was recorded for each task type? | L52: start_date, end_date | M52: Support governed management analysis. | N52: Task-type reference table must be confirmed. | O52: tbl_timesheets.project_task_type_id | P52: N/A | Q52: Governed multi-table query | R52: High | S52: Orbit KPI Tool with predefined metric logic; Mesh may explain results but must not calculate metrics freely | T52: Not Applicable – Non-Direct Support | V52: Task-type reference table must be confirmed.
A53: Existing – Retained | B53: 60 | C53: Delivery Head / Resource Manager / PM | D53: Medium | E53: Timesheets | F53: Exception / Diagnostic | G53: Complex | H53: users_without_time_entries | I53: Who has no timesheet entries for :date? | J53: Show users who did not log time on :date. | K53: List missing time entries for :date. | L53: date, population_scope | M53: Identify exceptions requiring owner action. | N53: Define expected population, working days, leave, and active users. | O53: tbl_users; tbl_timesheets | P53: N/A | Q53: Exception query with joins and threshold filters | R53: High | S53: Orbit KPI Tool with predefined metric logic; Mesh may explain results but must not calculate metrics freely | T53: Not Applicable – Non-Direct Support | V53: Define expected population, working days, leave, and active users.
A54: Existing – Retained | B54: 61 | C54: Delivery Head / Resource Manager / PM | D54: Medium | E54: Timesheets | F54: Exception / Diagnostic | G54: Complex | H54: daily_hours_above_threshold | I54: Who logged more than :hours_threshold hours on :date? | J54: Show high-hour timesheet entries. | K54: List users exceeding the daily-hours threshold. | L54: date, hours_threshold | M54: Identify exceptions requiring owner action. | N54: Threshold supplied at runtime. | O54: tbl_timesheets; users | P54: N/A | Q54: Exception query with joins and threshold filters | R54: High | S54: Orbit KPI Tool with predefined metric logic; Mesh may explain results but must not calculate metrics freely | T54: Not Applicable – Non-Direct Support | V54: Threshold supplied at runtime.
A55: Existing – Retained | B55: 62 | C55: Delivery Head / Resource Manager / PM | D55: Medium | E55: Timesheets | F55: KPI / Comparative | G55: Complex | H55: project_hours_vs_task_actual | I55: Compare timesheet hours with task actual hours for :project_name. | J55: Show discrepancies between booked time and task actual hours. | K55: Do task actuals match timesheet totals? | L55: project_name | M55: Support prioritisation and performance comparison. | N55: Clarify whether actual_hours is system-calculated or manually maintained. | O55: tbl_timesheets; tbl_project_tasks.actual_hours | P55: N/A | Q55: Multi-table derived KPI with controlled formula | R55: High | S55: Orbit KPI Tool with predefined metric logic; Mesh may explain results but must not calculate metrics freely | T55: Not Applicable – Non-Direct Support | V55: Clarify whether actual_hours is system-calculated or manually maintained.
A56: Existing – Retained | B56: 63 | C56: Delivery Head / Resource Manager / PM | D56: Medium | E56: Timesheets | F56: Derived Analysis | G56: Very Complex | H56: timesheet_approval_status | I56: What is the approval status of my timesheet? | J56: Show whether my timesheet is approved. | K56: Are my time entries pending approval? | L56: current_user, period | M56: Support governed management analysis. | N56: No approval/status field is present in tbl_timesheets. | O56: tbl_timesheets | P56: N/A | Q56: Governed multi-table query | R56: High | S56: Orbit KPI Tool with predefined metric logic; Mesh may explain results but must not calculate metrics freely | T56: Not Applicable – Non-Direct Support | V56: No approval/status field is present in tbl_timesheets.
A57: Existing – Retained | B57: 64 | C57: Delivery Head / Resource Manager / PM | D57: Medium | E57: Timesheets | F57: Derived Analysis | G57: Very Complex | H57: rejected_timesheets | I57: Which timesheets were rejected? | J57: Show rejected time entries. | K57: List declined timesheets. | L57: period | M57: Support governed management analysis. | N57: No rejection field or workflow table identified. | O57: tbl_timesheets | P57: N/A | Q57: Governed multi-table query | R57: High | S57: Orbit KPI Tool with predefined metric logic; Mesh may explain results but must not calculate metrics freely | T57: Not Applicable – Non-Direct Support | V57: No rejection field or workflow table identified.
A58: Existing – Retained | B58: 65 | C58: Delivery Head / Resource Manager / PM | D58: Low | E58: Resources | F58: Simple Lookup / Filter | G58: Simple | H58: my_project_allocations | I58: What projects am I allocated to? | J58: Show my current project allocations. | K58: List projects where I am a member. | L58: current_user, as_of_date | M58: Fast operational lookup and drill-down. | N58: Direct lookup/filter; no derived KPI. | O58: tbl_project_users; projects | P58: Data Available | Q58: Parameterized lookup/filter | R58: Low | S58: FAQ Tool Call Binding + parameterized SQL; cache intent/SQL, not live response | T58: Mapped – Direct Schema | U58: SELECT p.project_id, p.project_key, p.title, pu.access_type, pu.role_id, pu.allocation_from, pu.allocation_to, pu.allocation_hrs, pu.resource_type, pu.request_status FROM tbl_project_users pu JOIN tbl_projects p ON p.project_id = pu.project_id WHERE pu.user_id = :current_user_id AND pu.status = 1 AND pu.request_status = 'A' ORDER BY pu.allocation_from DESC, p.title; | V58: Use allocation dates and active status.
A59: Existing – Retained | B59: 66 | C59: Delivery Head / Resource Manager / PM | D59: Low | E59: Resources | F59: Simple Lookup / Filter | G59: Simple | H59: employee_allocations | I59: Show allocations for :employee_name. | J59: Which projects is :employee_name allocated to? | K59: List :employee_name’s project assignments. | L59: employee_name, as_of_date | M59: Fast operational lookup and drill-down. | N59: Direct lookup/filter; no derived KPI. | O59: tbl_project_users; users; projects | P59: Data Available | Q59: Parameterized lookup/filter | R59: Low | S59: FAQ Tool Call Binding + parameterized SQL; cache intent/SQL, not live response | T59: Mapped – Direct Schema | U59: SELECT u.user_id, CONCAT_WS(' ', u.first_name, u.last_name) AS employee_name, p.project_id, p.title AS project_title, pu.allocation_from, pu.allocation_to, pu.allocation_hrs, pu.resource_type, pu.access_type, pu.request_status FROM tbl_users u JOIN tbl_project_users pu ON pu.user_id = u.user_id JOIN tbl_projects p ON p.project_id = pu.project_id WHERE CONCAT_WS(' ', u.first_name, u.last_name) = :employee_name AND pu.status = 1 ORDER BY pu.allocation_from DESC, p.title; | V59: RBAC required.
A60: Existing – Retained | B60: 67 | C60: Delivery Head / Resource Manager / PM | D60: Low | E60: Resources | F60: Simple Lookup / Filter | G60: Simple | H60: project_team | I60: Who is allocated to :project_name? | J60: Show the team of :project_name. | K60: List project members for :project_name. | L60: project_name | M60: Fast operational lookup and drill-down. | N60: Direct lookup/filter; no derived KPI. | O60: tbl_project_users; users | P60: Data Available | Q60: Parameterized lookup/filter | R60: Low | S60: FAQ Tool Call Binding + parameterized SQL; cache intent/SQL, not live response | T60: Mapped – Direct Schema | U60: SELECT u.user_id, CONCAT_WS(' ', u.first_name, u.last_name) AS employee_name, u.email, pu.access_type, pu.role_id, pu.allocation_from, pu.allocation_to, pu.allocation_hrs, pu.resource_type, pu.request_status FROM tbl_projects p JOIN tbl_project_users pu ON pu.project_id = p.project_id JOIN tbl_users u ON u.user_id = pu.user_id WHERE p.title = :project_name AND pu.status = 1 ORDER BY employee_name; | V60: Filter active allocation and request status.
A61: Existing – Retained | B61: 68 | C61: Delivery Head / Resource Manager / PM | D61: Low | E61: Resources | F61: Simple Lookup / Filter | G61: Simple | H61: project_allocated_hours | I61: Show allocated hours by user for :project_name. | J61: How many hours is each user allocated to :project_name? | K61: List resource allocation hours for :project_name. | L61: project_name | M61: Fast operational lookup and drill-down. | N61: Direct lookup/filter; no derived KPI. | O61: tbl_project_users.allocation_hrs | P61: Data Available | Q61: Parameterized lookup/filter | R61: Low | S61: FAQ Tool Call Binding + parameterized SQL; cache intent/SQL, not live response | T61: Mapped – Direct Schema | U61: SELECT u.user_id, CONCAT_WS(' ', u.first_name, u.last_name) AS employee_name, pu.allocation_hrs, pu.allocation_from, pu.allocation_to, pu.resource_type FROM tbl_projects p JOIN tbl_project_users pu ON pu.project_id = p.project_id JOIN tbl_users u ON u.user_id = pu.user_id WHERE p.title = :project_name AND pu.status = 1 AND pu.request_status = 'A' ORDER BY pu.allocation_hrs DESC, employee_name; | V61: Confirm allocation_hrs period basis.
A62: Existing – Retained | B62: 69 | C62: Delivery Head / Resource Manager / PM | D62: Low | E62: Resources | F62: Simple Lookup / Filter | G62: Simple | H62: allocations_ending_soon | I62: Whose project allocation ends in the next :days days? | J62: Show allocations ending soon. | K62: List users rolling off projects soon. | L62: days | M62: Fast operational lookup and drill-down. | N62: Direct lookup/filter; no derived KPI. | O62: tbl_project_users.allocation_to | P62: Data Available | Q62: Parameterized lookup/filter | R62: Low | S62: FAQ Tool Call Binding + parameterized SQL; cache intent/SQL, not live response | T62: Mapped – Direct Schema | U62: SELECT u.user_id, CONCAT_WS(' ', u.first_name, u.last_name) AS employee_name, p.project_id, p.title AS project_title, pu.allocation_to, pu.allocation_hrs, pu.resource_type FROM tbl_project_users pu JOIN tbl_projects p ON p.project_id = pu.project_id JOIN tbl_users u ON u.user_id = pu.user_id WHERE pu.status = 1 AND pu.request_status = 'A' AND pu.allocation_to >= CURRENT_DATE AND pu.allocation_to < DATE_ADD(CURRENT_DATE, INTERVAL :days + 1 DAY) ORDER BY pu.allocation_to, employee_name; | V62: Active allocation filter required.
A63: Existing – Retained | B63: 70 | C63: Delivery Head / Resource Manager / PM | D63: Low | E63: Resources | F63: Simple Lookup / Filter | G63: Simple | H63: allocations_starting_soon | I63: Whose project allocation starts in the next :days days? | J63: Show upcoming allocations. | K63: List users joining projects soon. | L63: days | M63: Fast operational lookup and drill-down. | N63: Direct lookup/filter; no derived KPI. | O63: tbl_project_users.allocation_from | P63: Data Available | Q63: Parameterized lookup/filter | R63: Low | S63: FAQ Tool Call Binding + parameterized SQL; cache intent/SQL, not live response | T63: Mapped – Direct Schema | U63: SELECT u.user_id, CONCAT_WS(' ', u.first_name, u.last_name) AS employee_name, p.project_id, p.title AS project_title, pu.allocation_from, pu.allocation_to, pu.allocation_hrs, pu.resource_type FROM tbl_project_users pu JOIN tbl_projects p ON p.project_id = pu.project_id JOIN tbl_users u ON u.user_id = pu.user_id WHERE pu.status = 1 AND pu.request_status IN ('A','I') AND pu.allocation_from >= CURRENT_DATE AND pu.allocation_from < DATE_ADD(CURRENT_DATE, INTERVAL :days + 1 DAY) ORDER BY pu.allocation_from, employee_name; | V63: Active/request status filter required.
A64: Existing – Retained | B64: 71 | C64: Delivery Head / Resource Manager / PM | D64: Medium | E64: Resources | F64: Derived Analysis | G64: Very Complex | H64: resources_by_department | I64: Show active users in department :department_name. | J64: List department resources. | K64: Who belongs to :department_name? | L64: department_name | M64: Support governed management analysis. | N64: tbl_users does not expose a direct department_id in visible columns. | O64: tbl_users; department relationships | P64: N/A | Q64: Governed multi-table query | R64: High | S64: Orbit KPI Tool with predefined metric logic; Mesh may explain results but must not calculate metrics freely | T64: Not Applicable – Non-Direct Support | V64: tbl_users does not expose a direct department_id in visible columns.
A65: Existing – Retained | B65: 73 | C65: Delivery Head / Resource Manager / PM | D65: Low | E65: Resources | F65: Simple Lookup / Filter | G65: Simple | H65: resource_skills | I65: What skills does :employee_name have? | J65: Show :employee_name’s recorded skills. | K65: List skills for :employee_name. | L65: employee_name | M65: Fast operational lookup and drill-down. | N65: Direct lookup/filter; no derived KPI. | O65: tbl_user_skills; skill master to identify | P65: Data Available | Q65: Parameterized lookup/filter | R65: Low | S65: FAQ Tool Call Binding + parameterized SQL; cache intent/SQL, not live response | T65: Mapped – Direct Schema | U65: SELECT u.user_id, CONCAT_WS(' ', u.first_name, u.last_name) AS employee_name, s.id AS skill_id, s.name AS skill_name FROM tbl_users u JOIN tbl_user_skills us ON us.user_id = u.user_id JOIN tbl_master_skills s ON s.id = us.skill_id WHERE CONCAT_WS(' ', u.first_name, u.last_name) = :employee_name AND us.status = '1' AND s.status = '1' ORDER BY s.name; | V65: Skill reference table must be located/confirmed.
A66: Existing – Retained | B66: 74 | C66: Delivery Head / Resource Manager / PM | D66: Medium | E66: Resources | F66: Derived Analysis | G66: Complex | H66: available_by_skill | I66: Who with skill :skill_name is available between :start_date and :end_date? | J66: Find resources with :skill_name and no overlapping allocation. | K66: Show available :skill_name resources. | L66: skill_name, start_date, end_date | M66: Support governed management analysis. | N66: Define availability and allocation capacity. | O66: tbl_user_skills; tbl_project_users | P66: N/A | Q66: Governed multi-table query | R66: High | S66: Orbit KPI Tool with predefined metric logic; Mesh may explain results but must not calculate metrics freely | T66: Not Applicable – Non-Direct Support | V66: Define availability and allocation capacity.
A67: Existing – Retained | B67: 75 | C67: Delivery Head / Resource Manager / PM | D67: Medium | E67: Resources | F67: Derived Analysis | G67: Complex | H67: overlapping_allocations | I67: Which users have overlapping project allocations? | J67: Show resource allocation conflicts. | K67: List people assigned to overlapping project periods. | L67: date_range | M67: Support governed management analysis. | N67: Does not prove overallocation unless hours/capacity are defined. | O67: tbl_project_users | P67: N/A | Q67: Governed multi-table query | R67: High | S67: Orbit KPI Tool with predefined metric logic; Mesh may explain results but must not calculate metrics freely | T67: Not Applicable – Non-Direct Support | V67: Does not prove overallocation unless hours/capacity are defined.
A68: Existing – Retained | B68: 76 | C68: Delivery Head / Resource Manager / PM | D68: Low | E68: Resources | F68: Simple Lookup / Filter | G68: Simple | H68: project_roles | I68: Show project roles for :project_name. | J68: List users and role IDs on :project_name. | K68: Who has which role on :project_name? | L68: project_name | M68: Fast operational lookup and drill-down. | N68: Direct lookup/filter; no derived KPI. | O68: tbl_project_users.role_id; role master | P68: Data Available | Q68: Parameterized lookup/filter | R68: Low | S68: FAQ Tool Call Binding + parameterized SQL; cache intent/SQL, not live response | T68: Mapped – Direct Schema | U68: SELECT u.user_id, CONCAT_WS(' ', u.first_name, u.last_name) AS employee_name, pu.role_id, r.role_name, r.role_slug FROM tbl_projects p JOIN tbl_project_users pu ON pu.project_id = p.project_id JOIN tbl_users u ON u.user_id = pu.user_id LEFT JOIN tbl_roles r ON r.role_id = pu.role_id WHERE p.title = :project_name AND pu.status = 1 ORDER BY r.role_name, employee_name; | V68: Role labels require lookup table.
A69: Existing – Retained | B69: 77 | C69: Delivery Head / Resource Manager / PM | D69: Low | E69: Resources | F69: Simple Lookup / Filter | G69: Simple | H69: project_access_types | I69: Show access types for users on :project_name. | J69: Who has what access on :project_name? | K69: List project membership access levels. | L69: project_name | M69: Fast operational lookup and drill-down. | N69: Direct lookup/filter; no derived KPI. | O69: tbl_project_users.access_type | P69: Data Available | Q69: Parameterized lookup/filter | R69: Low | S69: FAQ Tool Call Binding + parameterized SQL; cache intent/SQL, not live response | T69: Mapped – Direct Schema | U69: SELECT pu.access_type, COUNT(*) AS user_count FROM tbl_projects p JOIN tbl_project_users pu ON pu.project_id = p.project_id WHERE p.title = :project_name AND pu.status = 1 GROUP BY pu.access_type ORDER BY pu.access_type; | V69: Enumerated values not available in schema.
A70: Existing – Retained | B70: 78 | C70: Delivery Head / Resource Manager / PM | D70: Medium | E70: Resources | F70: Derived Analysis | G70: Complex | H70: bench_resources | I70: Who is currently on the bench? | J70: Show users with no active project allocation. | K70: List unallocated active resources. | L70: as_of_date, population_scope | M70: Support governed management analysis. | N70: Define active employee population and whether no allocation means bench. | O70: tbl_users; tbl_project_users | P70: N/A | Q70: Governed multi-table query | R70: High | S70: Orbit KPI Tool with predefined metric logic; Mesh may explain results but must not calculate metrics freely | T70: Not Applicable – Non-Direct Support | V70: Define active employee population and whether no allocation means bench.
A71: Existing – Retained | B71: 79 | C71: Delivery Head / Resource Manager / PM | D71: Medium | E71: Utilization | F71: KPI / Comparative | G71: Complex | H71: allocation_utilization_user | I71: What is :employee_name’s allocation utilization for :period? | J71: Show allocated hours versus capacity for :employee_name. | K71: How utilized is :employee_name based on allocations? | L71: employee_name, period | M71: Support prioritisation and performance comparison. | N71: Capacity/working-hour calendar is not defined. | O71: tbl_project_users.allocation_hrs | P71: N/A | Q71: Multi-table derived KPI with controlled formula | R71: High | S71: Orbit KPI Tool with predefined metric logic; Mesh may explain results but must not calculate metrics freely | T71: Not Applicable – Non-Direct Support | V71: Capacity/working-hour calendar is not defined.
A72: Existing – Retained | B72: 80 | C72: Delivery Head / Resource Manager / PM | D72: Medium | E72: Utilization | F72: KPI / Comparative | G72: Complex | H72: timesheet_utilization_user | I72: What is :employee_name’s timesheet utilization for :period? | J72: Show logged hours versus available hours for :employee_name. | K72: How utilized is :employee_name based on timesheets? | L72: employee_name, period | M72: Support prioritisation and performance comparison. | N72: Working hours and leave calendar required. | O72: tbl_timesheets | P72: N/A | Q72: Multi-table derived KPI with controlled formula | R72: High | S72: Orbit KPI Tool with predefined metric logic; Mesh may explain results but must not calculate metrics freely | T72: Not Applicable – Non-Direct Support | V72: Working hours and leave calendar required.
A73: Existing – Retained | B73: 81 | C73: Delivery Head / Resource Manager / PM | D73: Medium | E73: Utilization | F73: KPI / Comparative | G73: Complex | H73: project_resource_utilization | I73: Show utilization of resources on :project_name. | J73: How utilized is the team on :project_name? | K73: List project utilization by member. | L73: project_name, period | M73: Support prioritisation and performance comparison. | N73: Choose allocation-based or timesheet-based method. | O73: project users; timesheets; tasks | P73: N/A | Q73: Multi-table derived KPI with controlled formula | R73: High | S73: Orbit KPI Tool with predefined metric logic; Mesh may explain results but must not calculate metrics freely | T73: Not Applicable – Non-Direct Support | V73: Choose allocation-based or timesheet-based method.
A74: Existing – Retained | B74: 82 | C74: Delivery Head / Resource Manager / PM | D74: Medium | E74: Utilization | F74: KPI / Comparative | G74: Complex | H74: low_utilization_users | I74: Who is below :threshold_percent utilization in :period? | J74: Show underutilized resources. | K74: List users below the utilization threshold. | L74: threshold_percent, period | M74: Support prioritisation and performance comparison. | N74: Capacity and population rules required. | O74: project users; timesheets | P74: N/A | Q74: Multi-table derived KPI with controlled formula | R74: High | S74: Orbit KPI Tool with predefined metric logic; Mesh may explain results but must not calculate metrics freely | T74: Not Applicable – Non-Direct Support | V74: Capacity and population rules required.
A75: Existing – Retained | B75: 83 | C75: Delivery Head / Resource Manager / PM | D75: Medium | E75: Utilization | F75: KPI / Comparative | G75: Complex | H75: high_utilization_users | I75: Who is above :threshold_percent utilization in :period? | J75: Show highly utilized resources. | K75: List users over the utilization threshold. | L75: threshold_percent, period | M75: Support prioritisation and performance comparison. | N75: Capacity and overtime rules required. | O75: project users; timesheets | P75: N/A | Q75: Multi-table derived KPI with controlled formula | R75: High | S75: Orbit KPI Tool with predefined metric logic; Mesh may explain results but must not calculate metrics freely | T75: Not Applicable – Non-Direct Support | V75: Capacity and overtime rules required.
A76: Existing – Retained | B76: 84 | C76: Delivery Head / Resource Manager / PM | D76: Medium | E76: Utilization | F76: KPI / Comparative | G76: Complex | H76: allocation_conflicts | I76: Who has allocations exceeding available capacity? | J76: Show overallocated users. | K76: List resource capacity conflicts. | L76: period | M76: Support prioritisation and performance comparison. | N76: Allocation hours period basis must be known. | O76: tbl_project_users.allocation_hrs | P76: N/A | Q76: Multi-table derived KPI with controlled formula | R76: High | S76: Orbit KPI Tool with predefined metric logic; Mesh may explain results but must not calculate metrics freely | T76: Not Applicable – Non-Direct Support | V76: Allocation hours period basis must be known.
A77: Existing – Retained | B77: 85 | C77: Delivery Head / Resource Manager / PM | D77: Medium | E77: Utilization | F77: KPI / Comparative | G77: Complex | H77: idle_capacity | I77: How much idle capacity is available in :period? | J77: Show unused resource capacity. | K77: What capacity remains unallocated? | L77: period, population_scope | M77: Support prioritisation and performance comparison. | N77: Requires working calendar and eligible population. | O77: project users; users | P77: N/A | Q77: Multi-table derived KPI with controlled formula | R77: High | S77: Orbit KPI Tool with predefined metric logic; Mesh may explain results but must not calculate metrics freely | T77: Not Applicable – Non-Direct Support | V77: Requires working calendar and eligible population.
A78: Existing – Retained | B78: 86 | C78: Delivery Head / Resource Manager / PM | D78: Medium | E78: Utilization | F78: KPI / Comparative | G78: Complex | H78: utilization_by_role | I78: Show utilization by project role for :period. | J78: Compare resource utilization across roles. | K78: What is utilization by role? | L78: period | M78: Support prioritisation and performance comparison. | N78: Role master and capacity formula required. | O78: project users.role_id; timesheets | P78: N/A | Q78: Multi-table derived KPI with controlled formula | R78: High | S78: Orbit KPI Tool with predefined metric logic; Mesh may explain results but must not calculate metrics freely | T78: Not Applicable – Non-Direct Support | V78: Role master and capacity formula required.
A79: Existing – Retained | B79: 87 | C79: Delivery Head / Resource Manager / PM | D79: Medium | E79: Utilization | F79: KPI / Comparative | G79: Complex | H79: utilization_by_department | I79: Show utilization for department :department_name in :period. | J79: How utilized is :department_name? | K79: Give department utilization. | L79: department_name, period | M79: Support prioritisation and performance comparison. | N79: User-department mapping must be confirmed. | O79: users; project users; timesheets | P79: N/A | Q79: Multi-table derived KPI with controlled formula | R79: High | S79: Orbit KPI Tool with predefined metric logic; Mesh may explain results but must not calculate metrics freely | T79: Not Applicable – Non-Direct Support | V79: User-department mapping must be confirmed.
A80: Existing – Retained | B80: 88 | C80: Delivery Head / Resource Manager / PM | D80: High | E80: Utilization | F80: Forecast / Predictive | G80: Complex | H80: forecast_utilization | I80: What is forecast utilization for :future_period? | J80: Show expected resource utilization next month. | K80: Forecast allocation-based utilization. | L80: future_period | M80: Support proactive intervention before delivery failure. | N80: Only allocation-based forecast appears possible from schema. | O80: tbl_project_users allocation dates/hours | P80: N/A | Q80: Composite score / forecast tool using deterministic indicators | R80: High | S80: Orbit KPI/Watchlist Tool with fixed scoring logic; optional Mesh explanation after computation | T80: Not Applicable – Non-Direct Support | V80: Only allocation-based forecast appears possible from schema.
A81: Existing – Retained | B81: 89 | C81: CEO / Delivery Head / Finance | D81: High | E81: Estimation & Financials | F81: Simple Lookup / Filter | G81: Simple | H81: project_estimate | I81: What is the estimate for :project_name? | J81: Show the project estimate value. | K81: How much effort is estimated for :project_name? | L81: project_name | M81: Fast operational lookup and drill-down. | N81: Direct lookup/filter; no derived KPI. | O81: tbl_projects.estimate | P81: Data Available | Q81: Parameterized lookup/filter | R81: Low | S81: FAQ Tool Call Binding + parameterized SQL; cache intent/SQL, not live response | T81: Mapped – Direct Schema | U81: SELECT p.project_id, p.project_key, p.title, p.estimate AS estimated_hours, p.is_approved FROM tbl_projects p WHERE p.title = :project_name AND p.status = 1 AND p.archive = 0 ORDER BY p.project_id; | V81: Confirm whether estimate is hours, days, or cost.
A82: Existing – Retained | B82: 90 | C82: CEO / Delivery Head / Finance | D82: High | E82: Estimation & Financials | F82: Aggregation / Dashboard KPI | G82: Moderate | H82: project_hours_summary | I82: Show total booked and chargeable hours for :project_name. | J82: What are the booked versus chargeable hours? | K82: Summarize project hour totals. | L82: project_name | M82: Provide a reusable dashboard metric for monitoring. | N82: Confirm refresh/source logic. | O82: tbl_projects.total_hours_booked; total_chargable_hours | P82: Data Available | Q82: Predefined aggregation / grouped KPI query | R82: Medium | S82: FAQ/NL2SQL cached template or Orbit aggregation tool; execute on live data | T82: Mapped – Direct Schema | U82: SELECT p.project_id, p.project_key, p.title, p.estimate AS estimated_hours, p.total_hours_booked, p.total_chargable_hours, p.grant_hours, p.combined_hours FROM tbl_projects p WHERE p.title = :project_name AND p.status = 1 AND p.archive = 0 ORDER BY p.project_id; | V82: Confirm refresh/source logic.
A83: Existing – Retained | B83: 91 | C83: CEO / Delivery Head / Finance | D83: High | E83: Estimation & Financials | F83: Aggregation / Dashboard KPI | G83: Complex | H83: project_grant_hours | I83: How many grant hours does :project_name have? | J83: Show available grant hours. | K83: What are the granted hours for :project_name? | L83: project_name | M83: Provide a reusable dashboard metric for monitoring. | N83: grant_hours was visible in archive/backup; confirm current tbl_projects column. | O83: tbl_projects archive/backup grant_hours | P83: N/A | Q83: Predefined aggregation / grouped KPI query | R83: High | S83: Orbit KPI Tool with predefined metric logic; Mesh may explain results but must not calculate metrics freely | T83: Not Applicable – Non-Direct Support | V83: grant_hours was visible in archive/backup; confirm current tbl_projects column.
A84: Existing – Retained | B84: 92 | C84: CEO / Delivery Head / Finance | D84: High | E84: Estimation & Financials | F84: Derived Analysis | G84: Very Complex | H84: project_deal_value | I84: What is the deal value of :project_name? | J84: Show the commercial value of :project_name. | K84: What value is recorded for :project_name? | L84: project_name | M84: Support governed management analysis. | N84: Confirm currency and financial RBAC. | O84: tbl_projects.deal_value | P84: N/A | Q84: Governed multi-table query | R84: High | S84: Orbit KPI Tool with predefined metric logic; Mesh may explain results but must not calculate metrics freely | T84: Not Applicable – Non-Direct Support | V84: Confirm currency and financial RBAC.
A85: Existing – Retained | B85: 98 | C85: CEO / Delivery Head / Finance | D85: High | E85: Estimation & Financials | F85: Aggregation / Dashboard KPI | G85: Moderate | H85: infrastructure_cost_summary | I85: Show infrastructure cost estimates for :project_name. | J85: What monthly infrastructure cost is recorded? | K85: Summarize infrastructure requirement costs. | L85: project_name | M85: Provide a reusable dashboard metric for monitoring. | N85: Currency not explicit. | O85: project_requirements_lineitem; infrastructure requirements | P85: Data Available | Q85: Predefined aggregation / grouped KPI query | R85: Medium | S85: FAQ/NL2SQL cached template or Orbit aggregation tool; execute on live data | T85: Mapped – Direct Schema | U85: SELECT ir.requirements_id, ir.project_id, ir.tag, ir.provided_by, li.service_category, li.tennancy, li.instance_type, li.region, li.operating_system, li.vcpu, li.memory, li.storage, li.cost, li.monthly_cost, li.version FROM tbl_projects p JOIN project_infrastructure_requirements ir ON ir.project_id = p.project_id JOIN project_requirements_lineitem li ON li.requirements_id = ir.requirements_id WHERE p.title = :project_name ORDER BY ir.requirements_id, li.sl_no; | V85: Currency not explicit.
A86: Existing – Retained | B86: 99 | C86: CEO / Delivery Head / Finance | D86: High | E86: Estimation & Financials | F86: KPI / Comparative | G86: Complex | H86: project_budget_status | I86: What is the budget status of :project_name? | J86: How much project budget remains? | K86: Is :project_name within budget? | L86: project_name | M86: Support prioritisation and performance comparison. | N86: No explicit approved budget, actual cost, or remaining budget fields identified. | O86: project/estimation tables | P86: N/A | Q86: Multi-table derived KPI with controlled formula | R86: High | S86: Orbit KPI Tool with predefined metric logic; Mesh may explain results but must not calculate metrics freely | T86: Not Applicable – Non-Direct Support | V86: No explicit approved budget, actual cost, or remaining budget fields identified.
A87: Existing – Retained | B87: 100 | C87: CEO / Delivery Head / Finance | D87: High | E87: Estimation & Financials | F87: KPI / Comparative | G87: Complex | H87: project_margin | I87: What is the margin of :project_name? | J87: Show revenue minus project cost. | K87: Is :project_name profitable? | L87: project_name | M87: Support prioritisation and performance comparison. | N87: Complete cost model and currency rules are absent. | O87: tbl_projects.deal_value; partial cost data | P87: N/A | Q87: Multi-table derived KPI with controlled formula | R87: High | S87: Orbit KPI Tool with predefined metric logic; Mesh may explain results but must not calculate metrics freely | T87: Not Applicable – Non-Direct Support | V87: Complete cost model and currency rules are absent.
A88: Existing – Retained | B88: 101 | C88: Delivery Head / PM / Risk or Issue Owner | D88: Medium | E88: Risks | F88: Derived Analysis | G88: Complex | H88: open_project_risks | I88: What are the open risks for :project_name? | J88: Show unresolved risks on :project_name. | K88: List active project risks. | L88: project_name | M88: Support governed management analysis. | N88: Define open risk statuses. | O88: tbl_risk; tbl_risk_status | P88: N/A | Q88: Governed multi-table query | R88: High | S88: Orbit KPI Tool with predefined metric logic; Mesh may explain results but must not calculate metrics freely | T88: Not Applicable – Non-Direct Support | V88: Define open risk statuses.
A89: Existing – Retained | B89: 102 | C89: Delivery Head / PM / Risk or Issue Owner | D89: Low | E89: Risks | F89: Simple Lookup / Filter | G89: Simple | H89: high_priority_risks | I89: Which risks are high priority? | J89: Show critical project risks. | K89: List the highest-priority risks. | L89: project_scope | M89: Fast operational lookup and drill-down. | N89: Direct lookup/filter; no derived KPI. | O89: tbl_risk.risk_priority_id; tbl_risk_priority | P89: Data Available | Q89: Parameterized lookup/filter | R89: Low | S89: FAQ Tool Call Binding + parameterized SQL; cache intent/SQL, not live response | T89: Mapped – Direct Schema | U89: SELECT r.risk_id, r.reference_no, r.title, p.title AS project_title, rp.priority_name, r.rating, r.rating_color_code, r.target_closure_date, rs.status_name FROM tbl_risk r JOIN tbl_projects p ON p.project_id = r.project_id LEFT JOIN tbl_risk_priority rp ON rp.risk_priority_id = r.risk_priority_id LEFT JOIN tbl_risk_status rs ON rs.status_id = r.status_id WHERE LOWER(rp.priority_name) = 'high' AND r.status = 1 ORDER BY r.rating DESC, r.target_closure_date; | V89: Lookup values required.
A90: Existing – Retained | B90: 103 | C90: Delivery Head / PM / Risk or Issue Owner | D90: Low | E90: Risks | F90: Simple Lookup / Filter | G90: Simple | H90: risk_details | I90: Show details of risk :risk_reference. | J90: Give me the risk record for :risk_reference. | K90: Open risk :risk_reference. | L90: risk_reference | M90: Fast operational lookup and drill-down. | N90: Direct lookup/filter; no derived KPI. | O90: tbl_risk | P90: Data Available | Q90: Parameterized lookup/filter | R90: Low | S90: FAQ Tool Call Binding + parameterized SQL; cache intent/SQL, not live response | T90: Mapped – Direct Schema | U90: SELECT r.risk_id, r.reference_no, r.title, r.description, r.cause, r.consequence, r.controls, r.action, p.title AS project_title, pr.probability_name, ri.impact_name, rp.priority_name, r.rating, r.rating_color_code, rs.status_name, r.owner_id, r.target_closure_date, r.revised_target_closure_date, r.date_raised, r.update_date FROM tbl_risk r JOIN tbl_projects p ON p.project_id = r.project_id LEFT JOIN tbl_risk_probability pr ON pr.probability_id = r.probability_id LEFT JOIN tbl_risk_impact ri ON ri.impact_id = r.impact_id LEFT JOIN tbl_risk_priority rp ON rp.risk_priority_id = r.risk_priority_id LEFT JOIN tbl_risk_status rs ON rs.status_id = r.status_id WHERE r.reference_no = :risk_reference AND r.status = 1; | V90: Use reference_no.
A91: Existing – Retained | B91: 104 | C91: Delivery Head / PM / Risk or Issue Owner | D91: Low | E91: Risks | F91: Simple Lookup / Filter | G91: Simple | H91: risks_by_probability | I91: Show risks by probability. | J91: Group active risks by probability rating. | K91: How many risks are in each probability level? | L91: project_scope | M91: Fast operational lookup and drill-down. | N91: Direct lookup/filter; no derived KPI. | O91: tbl_risk; tbl_risk_probability | P91: Data Available | Q91: Parameterized lookup/filter | R91: Low | S91: FAQ Tool Call Binding + parameterized SQL; cache intent/SQL, not live response | T91: Mapped – Direct Schema | U91: SELECT pr.probability_id, pr.probability_name, pr.probability_value, COUNT(*) AS risk_count FROM tbl_risk r LEFT JOIN tbl_risk_probability pr ON pr.probability_id = r.probability_id WHERE r.status = 1 GROUP BY pr.probability_id, pr.probability_name, pr.probability_value ORDER BY pr.probability_value DESC; | V91: Lookup values required.
A92: Existing – Retained | B92: 105 | C92: Delivery Head / PM / Risk or Issue Owner | D92: Low | E92: Risks | F92: Simple Lookup / Filter | G92: Simple | H92: risks_by_impact | I92: Show risks by impact. | J92: Group active risks by impact rating. | K92: How many risks are in each impact level? | L92: project_scope | M92: Fast operational lookup and drill-down. | N92: Direct lookup/filter; no derived KPI. | O92: tbl_risk; tbl_risk_impact | P92: Data Available | Q92: Parameterized lookup/filter | R92: Low | S92: FAQ Tool Call Binding + parameterized SQL; cache intent/SQL, not live response | T92: Mapped – Direct Schema | U92: SELECT ri.impact_id, ri.impact_name, ri.impact_value, COUNT(*) AS risk_count FROM tbl_risk r LEFT JOIN tbl_risk_impact ri ON ri.impact_id = r.impact_id WHERE r.status = 1 GROUP BY ri.impact_id, ri.impact_name, ri.impact_value ORDER BY ri.impact_value DESC; | V92: Lookup values required.
A93: Existing – Retained | B93: 106 | C93: Delivery Head / PM / Risk or Issue Owner | D93: Medium | E93: Risks | F93: Exception / Diagnostic | G93: Moderate | H93: risks_without_owner | I93: Which risks have no owner? | J93: Show unassigned risks. | K93: List risks without responsibility. | L93: project_scope | M93: Identify exceptions requiring owner action. | N93: Confirm owner_id versus responsibility. | O93: tbl_risk.owner_id/responsibility | P93: Data Available | Q93: Exception query with joins and threshold filters | R93: Medium | S93: FAQ/NL2SQL cached template or Orbit aggregation tool; execute on live data | T93: Mapped – Direct Schema | U93: SELECT r.risk_id, r.reference_no, r.title, p.title AS project_title, r.owner_id, r.responsibility, r.target_closure_date FROM tbl_risk r JOIN tbl_projects p ON p.project_id = r.project_id WHERE (r.owner_id = 0 OR r.owner_id IS NULL) AND r.status = 1 ORDER BY r.target_closure_date, r.reference_no; | V93: Confirm owner_id versus responsibility.
A94: Existing – Retained | B94: 107 | C94: Delivery Head / PM / Risk or Issue Owner | D94: Medium | E94: Risks | F94: Derived Analysis | G94: Very Complex | H94: risk_actions_due | I94: Which risk actions are due by :date? | J94: Show mitigation work due soon. | K94: List risk actions approaching target closure. | L94: date | M94: Support governed management analysis. | N94: Mitigation actions table lacks explicit due date. | O94: tbl_risk.target_closure_date; mitigation plans | P94: N/A | Q94: Governed multi-table query | R94: High | S94: Orbit KPI Tool with predefined metric logic; Mesh may explain results but must not calculate metrics freely | T94: Not Applicable – Non-Direct Support | V94: Mitigation actions table lacks explicit due date.
A95: Existing – Retained | B95: 108 | C95: Delivery Head / PM / Risk or Issue Owner | D95: Medium | E95: Risks | F95: Exception / Diagnostic | G95: Complex | H95: overdue_risks | I95: Which open risks are past their target closure date? | J95: Show overdue unresolved risks. | K95: List risks missing target closure. | L95: as_of_date | M95: Identify exceptions requiring owner action. | N95: Define closed statuses and revised date precedence. | O95: tbl_risk; risk status | P95: N/A | Q95: Exception query with joins and threshold filters | R95: High | S95: Orbit KPI Tool with predefined metric logic; Mesh may explain results but must not calculate metrics freely | T95: Not Applicable – Non-Direct Support | V95: Define closed statuses and revised date precedence.
A96: Existing – Reworked with Populated Alternative | B96: 109 | C96: Delivery Head / PM / Risk or Issue Owner | D96: Medium | E96: Risks | F96: Trend / Change Analysis | G96: Moderate | H96: risk_history | I96: Show the recorded history of risk :risk_reference. | J96: How has risk :risk_reference changed over time? | K96: Show status, probability, and impact history for :risk_reference. | L96: risk_reference | M96: Detect deterioration or improvement over time. | N96: Use populated tbl_risk_history instead of empty tbl_risk_update. | O96: tbl_risk; tbl_risk_history; tbl_risk_status; tbl_risk_probability; tbl_risk_impact; tbl_users | P96: Available – Alternative History Table | Q96: Time-series aggregation across populated history/date fields | R96: Medium | S96: FAQ/NL2SQL cached template or Orbit aggregation tool; execute on live data | T96: Mapped – Populated Alternative | U96: SELECT r.reference_no, rh.post_date, rs.status_name, rp.probability_name, ri.impact_name, u.username AS changed_by FROM tbl_risk r JOIN tbl_risk_history rh ON rh.risk_id = r.risk_id LEFT JOIN tbl_risk_status rs ON rs.status_id = rh.status_id LEFT JOIN tbl_risk_probability rp ON rp.probability_id = rh.probability_id LEFT JOIN tbl_risk_impact ri ON ri.impact_id = rh.impact_id LEFT JOIN tbl_users u ON u.user_id = rh.user_id WHERE r.reference_no = :risk_reference ORDER BY rh.post_date DESC; | V96: Use populated tbl_risk_history instead of empty tbl_risk_update. Recovered from empty-table dependency.
A97: Existing – Retained | B97: 110 | C97: Delivery Head / PM / Risk or Issue Owner | D97: Medium | E97: Risks | F97: Trend / Change Analysis | G97: Complex | H97: risk_trend | I97: Show risk creation and closure trend for the last :months months. | J97: How are open risks trending? | K97: Give monthly risk movement. | L97: months | M97: Detect deterioration or improvement over time. | N97: Clarify point-in-time open count versus event counts. | O97: tbl_risk.date_raised/date_closed | P97: N/A | Q97: Time-series aggregation across populated history/date fields | R97: High | S97: Orbit KPI Tool with predefined metric logic; Mesh may explain results but must not calculate metrics freely | T97: Not Applicable – Non-Direct Support | V97: Clarify point-in-time open count versus event counts.
A98: Existing – Retained | B98: 111 | C98: Delivery Head / PM / Risk or Issue Owner | D98: Medium | E98: Issues & Reporting | F98: Derived Analysis | G98: Complex | H98: open_project_issues | I98: What are the open issues for :project_name? | J98: Show unresolved issues on :project_name. | K98: List active project issues. | L98: project_name | M98: Support governed management analysis. | N98: Define open issue statuses. | O98: tbl_project_issues; issue status | P98: N/A | Q98: Governed multi-table query | R98: High | S98: Orbit KPI Tool with predefined metric logic; Mesh may explain results but must not calculate metrics freely | T98: Not Applicable – Non-Direct Support | V98: Define open issue statuses.
A99: Existing – Retained | B99: 112 | C99: Delivery Head / PM / Risk or Issue Owner | D99: Low | E99: Issues & Reporting | F99: Simple Lookup / Filter | G99: Simple | H99: issue_details | I99: Show details of issue :issue_reference. | J99: Give me the issue record for :issue_reference. | K99: Open issue :issue_reference. | L99: issue_reference | M99: Fast operational lookup and drill-down. | N99: Direct lookup/filter; no derived KPI. | O99: tbl_project_issues | P99: Data Available | Q99: Parameterized lookup/filter | R99: Low | S99: FAQ Tool Call Binding + parameterized SQL; cache intent/SQL, not live response | T99: Mapped – Direct Schema | U99: SELECT i.issue_id, i.reference_no, i.title, i.description, p.title AS project_title, i.user_id AS raised_by_user_id, i.date_raised, i.date_closed, i.issue_status_id, s.status_name, i.severity, i.priority, i.impact, i.planned_closure_date, i.overdue_status, i.update_date FROM tbl_project_issues i JOIN tbl_projects p ON p.project_id = i.project_id LEFT JOIN tbl_project_issue_status s ON s.issue_status_id = i.issue_status_id WHERE i.reference_no = :issue_reference AND i.status = 1; | V99: Use reference_no.
A100: Existing – Retained | B100: 113 | C100: Delivery Head / PM / Risk or Issue Owner | D100: Medium | E100: Issues & Reporting | F100: Simple Lookup / Filter | G100: Moderate | H100: high_severity_issues | I100: Which issues have high severity? | J100: Show critical defects or issues. | K100: List high-severity open issues. | L100: project_scope | M100: Fast operational lookup and drill-down. | N100: Direct lookup/filter; no derived KPI. | O100: tbl_project_issues.severity | P100: N/A | Q100: Parameterized lookup/filter | R100: Medium | S100: FAQ/NL2SQL cached template or Orbit aggregation tool; execute on live data | T100: Not Mapped – Lookup Values Required | V100: Severity values are not supplied.
...

Sheet Executive KPI Questions
A1: Source | B1: Original ID | C1: Audience | D1: Executive Priority | E1: PMS Area | F1: Question Type | G1: Complexity Tag | H1: Canonical Intent | I1: Primary Question | J1: Alternative Phrasing 1 | K1: Alternative Phrasing 2 | L1: Required Parameters | M1: Business Decision / Value | N1: KPI / Derivation Logic | O1: Relevant Populated Tables | P1: Data Readiness | Q1: Query Strategy | R1: LLM Error Risk | S1: Recommended Execution / Cache | T1: Query Mapping Status | U1: SQL Query (Existing or Recovered) | V1: Notes
A2: New – Executive / KPI / Dashboard | C2: CEO / Executive Committee | D2: High | E2: Executive Portfolio | F2: Executive Composite KPI | G2: Very Complex | H2: executive_attention_ranking | I2: Which projects require immediate executive attention, ranked from highest to lowest risk? | J2: Show the top :top_n projects needing leadership intervention. | K2: Create an executive exception list for the portfolio. | L2: as_of_date; top_n; scoring_weights | M2: Focus leadership time on the projects with the largest combined delivery exposure. | N2: Composite score using project RAG, overdue-task ratio, high-severity/open issues, current risk exposure, effort burn, days to end date, and stale-update penalties. | O2: tbl_projects; tbl_project_status; tbl_project_stages; tbl_project_tasks; tbl_project_task_status; tbl_project_issues; tbl_project_issue_status; tbl_risk; tbl_risk_status; tbl_risk_probability; tbl_risk_impact | P2: Available – KPI Rule Required | Q2: Composite multi-table ranking | R2: High | S2: Orbit KPI/Watchlist Tool with fixed formulas; cache intent/query plan, execute against live data; use Mesh only to explain computed results. | T2: Pending – Complex KPI SQL Design
A3: New – Executive / KPI / Dashboard | C3: CEO / Executive Committee / Finance | D3: High | E3: Executive Portfolio | F3: Executive KPI / Dashboard | G3: Complex | H3: deal_weighted_rag_distribution | I3: What percentage of the active portfolio is Red, Amber, or Green when weighted by deal value? | J3: Show deal-value-weighted RAG distribution. | K3: How much portfolio value sits in each RAG category? | L3: as_of_date | M3: Measure financial exposure, not only project counts. | N3: Sum deal_value by RAG and divide by total deal_value for active, non-archived projects. | O3: tbl_projects | P3: Available – KPI Rule Required | Q3: Predefined multi-table KPI / trend aggregation | R3: High | S3: Orbit KPI/Watchlist Tool with fixed formulas; cache intent/query plan, execute against live data; use Mesh only to explain computed results. | T3: Pending – Complex KPI SQL Design
A4: New – Executive / KPI / Dashboard | C4: CEO / Executive Committee / Finance | D4: High | E4: Executive Portfolio | F4: Executive KPI / Dashboard | G4: Complex | H4: deal_value_at_risk | I4: How much deal value is currently at risk in Red and Amber projects? | J4: Show total commercial exposure in unhealthy projects. | K4: What is the value of the portfolio requiring recovery action? | L4: as_of_date; risk_rag_values | M4: Quantify commercial exposure and prioritise recovery investment. | N4: Aggregate deal_value for active projects whose RAG is in configured risk categories; split by PM, client, project type, and stage. | O4: tbl_projects; tbl_clients; tbl_project_types; tbl_project_stages | P4: Available – KPI Rule Required | Q4: Predefined multi-table KPI / trend aggregation | R4: High | S4: Orbit KPI/Watchlist Tool with fixed formulas; cache intent/query plan, execute against live data; use Mesh only to explain computed results. | T4: Pending – Complex KPI SQL Design
A5: New – Executive / KPI / Dashboard | C5: CEO / Delivery Head / Portfolio Head | D5: High | E5: Executive Portfolio | F5: Forecast / Predictive | G5: Very Complex | H5: project_end_date_miss_forecast | I5: Which projects are most likely to miss their committed end dates? | J5: Forecast projects at risk of schedule slippage. | K5: Which projects need intervention to protect their delivery date? | L5: as_of_date; forecast_horizon; scoring_weights | M5: Intervene before delivery dates are missed. | N5: Deterministic risk score using days remaining, overdue/open-task ratio, tasks due after project end, remaining estimated effort, unresolved issue/risk exposure, and update recency. | O5: tbl_projects; tbl_project_status; tbl_project_stages; tbl_project_tasks; tbl_project_task_status; tbl_timesheets; tbl_project_issues; tbl_project_issue_status; tbl_risk; tbl_risk_status | P5: Available – KPI Rule Required | Q5: Deterministic forecast / watchlist scoring | R5: High | S5: Orbit KPI/Watchlist Tool with fixed formulas; cache intent/query plan, execute against live data; use Mesh only to explain computed results. | T5: Pending – Complex KPI SQL Design
A6: New – Executive / KPI / Dashboard | C6: CEO / Delivery Head | D6: High | E6: Executive Portfolio | F6: Executive KPI / Dashboard | G6: Complex | H6: pm_risk_concentration | I6: Which project managers carry the highest concentration of Red or Amber projects? | J6: Rank PMs by unhealthy project count and value. | K6: Which PM portfolios need additional leadership support? | L6: as_of_date; rag_values | M6: Detect concentrated delivery risk and coaching/support needs. | N6: Group active projects by pm_user_id; calculate red/amber project count, percentage, deal value, overdue-task ratio, and issue/risk exposure. | O6: tbl_projects; tbl_users; tbl_project_tasks; tbl_project_issues; tbl_risk | P6: Available – KPI Rule Required | Q6: Predefined multi-table KPI / trend aggregation | R6: High | S6: Orbit KPI/Watchlist Tool with fixed formulas; cache intent/query plan, execute against live data; use Mesh only to explain computed results. | T6: Pending – Complex KPI SQL Design
A7: New – Executive / KPI / Dashboard | C7: CEO / Delivery Head | D7: High | E7: Executive Portfolio | F7: Executive Composite KPI | G7: Very Complex | H7: pm_delivery_performance_scorecard | I7: How are project managers performing across delivery, effort, risk, and issue KPIs? | J7: Show a comparative PM delivery scorecard. | K7: Which PMs consistently deliver healthy projects? | L7: period; scoring_weights; minimum_project_count | M7: Compare performance using consistent evidence rather than narrative judgement. | N7: Composite PM score from project RAG, on-time task rate, average overdue days, effort variance, issue closure rate, risk closure rate, and update freshness. | O7: tbl_projects; tbl_users; tbl_project_tasks; tbl_project_task_status; tbl_timesheets; tbl_project_issues; tbl_project_issue_status; tbl_risk; tbl_risk_status | P7: Available – KPI Rule Required | Q7: Composite multi-table ranking | R7: High | S7: Orbit KPI/Watchlist Tool with fixed formulas; cache intent/query plan, execute against live data; use Mesh only to explain computed results. | T7: Pending – Complex KPI SQL Design
A8: New – Executive / KPI / Dashboard | C8: CEO / Delivery Head / Finance | D8: High | E8: Executive Portfolio | F8: Executive KPI / Dashboard | G8: Complex | H8: portfolio_effort_burn_vs_completion | I8: Which projects are consuming effort faster than they are completing work? | J8: Compare effort burn against delivery completion across the portfolio. | K8: Where is effort consumption outpacing progress? | L8: as_of_date; burn_threshold; completion_method | M8: Identify likely overruns early. | N8: Compare project estimate, total_hours_booked, timesheet hours, and weighted task percent_complete. Flag high burn with low completion. | O8: tbl_projects; tbl_project_tasks; tbl_timesheets | P8: Available – KPI Rule Required | Q8: Predefined multi-table KPI / trend aggregation | R8: High | S8: Orbit KPI/Watchlist Tool with fixed formulas; cache intent/query plan, execute against live data; use Mesh only to explain computed results. | T8: Pending – Complex KPI SQL Design
A9: New – Executive / KPI / Dashboard | C9: CEO / Delivery Head / Finance | D9: High | E9: Executive Portfolio | F9: Exception / KPI | G9: Complex | H9: high_burn_low_completion_projects | I9: Which projects have consumed more than :burn_percent of estimated effort but completed less than :completion_percent of work? | J9: Find high-burn, low-progress projects. | K9: Which projects show the strongest effort-to-progress mismatch? | L9: burn_percent; completion_percent; as_of_date | M9: Create a focused overrun watchlist. | N9: Burn ratio = live logged/booked effort ÷ project estimate. Completion = governed weighted task completion. Filter using configured thresholds. | O9: tbl_projects; tbl_project_tasks; tbl_timesheets | P9: Available – KPI Rule Required | Q9: Predefined multi-table KPI / trend aggregation | R9: High | S9: Orbit KPI/Watchlist Tool with fixed formulas; cache intent/query plan, execute against live data; use Mesh only to explain computed results. | T9: Pending – Complex KPI SQL Design
A10: New – Executive / KPI / Dashboard | C10: CEO / Client Leadership / Delivery Head | D10: High | E10: Executive Portfolio | F10: Executive Composite KPI | G10: Very Complex | H10: client_delivery_exposure | I10: Which clients have the greatest delivery exposure across active projects? | J10: Rank clients by project value, unhealthy RAG, overdue work, risks, and issues. | K10: Where is client relationship risk concentrated? | L10: as_of_date; top_n | M10: Protect strategic client relationships and revenue. | N10: Aggregate project count, deal value, RAG mix, overdue-task ratio, issue severity, and risk exposure by client. | O10: tbl_projects; tbl_clients; tbl_project_tasks; tbl_project_issues; tbl_risk | P10: Available – KPI Rule Required | Q10: Composite multi-table ranking | R10: High | S10: Orbit KPI/Watchlist Tool with fixed formulas; cache intent/query plan, execute against live data; use Mesh only to explain computed results. | T10: Pending – Complex KPI SQL Design
A11: New – Executive / KPI / Dashboard | C11: CEO / Strategy / Delivery Head | D11: High | E11: Executive Portfolio | F11: Executive KPI / Dashboard | G11: Complex | H11: portfolio_segment_performance | I11: Which project types, business models, sources, or categories have the highest delay and overrun rates? | J11: Compare delivery performance across portfolio segments. | K11: Which types of work are structurally underperforming? | L11: period; segment_dimension; minimum_project_count | M11: Improve portfolio strategy, pricing, and delivery model choices. | N11: Group by project_type/project_type_id, business_model, source, or category_type; compare overdue rate, RAG mix, effort variance, issue rate, and risk exposure. | O11: tbl_projects; tbl_project_types; tbl_project_tasks; tbl_timesheets; tbl_project_issues; tbl_risk | P11: Available – KPI Rule Required | Q11: Predefined multi-table KPI / trend aggregation | R11: High | S11: Orbit KPI/Watchlist Tool with fixed formulas; cache intent/query plan, execute against live data; use Mesh only to explain computed results. | T11: Pending – Complex KPI SQL Design
A12: New – Executive / KPI / Dashboard | C12: CEO / Audit / Delivery Head | D12: High | E12: Governance | F12: Executive KPI / Dashboard | G12: Complex | H12: high_value_governance_gaps | I12: Which high-value projects have unresolved governance or audit gaps? | J12: Show projects with pending/review audit status and high deal value. | K12: Where are governance gaps creating material exposure? | L12: deal_value_threshold; as_of_date | M12: Prioritise governance remediation on materially important projects. | N12: Filter projects with audit_status not confirmed or missing/blank lifecycle evidence fields; rank by deal_value and health indicators. | O12: tbl_projects | P12: Available – KPI Rule Required | Q12: Predefined multi-table KPI / trend aggregation | R12: High | S12: Orbit KPI/Watchlist Tool with fixed formulas; cache intent/query plan, execute against live data; use Mesh only to explain computed results. | T12: Pending – Complex KPI SQL Design
A13: New – Executive / KPI / Dashboard | C13: CEO / Delivery Head / PMO | D13: High | E13: Executive Reporting | F13: Exception / KPI | G13: Complex | H13: executive_summary_freshness | I13: Which active projects have stale or missing executive summaries? | J13: Show projects without a recent management update. | K13: Which projects have not provided an executive summary within :days days? | L13: days; as_of_date | M13: Improve management visibility and reporting discipline. | N13: For each active project, compare latest tbl_project_executive_summary.save_date/post_date with as_of_date; rank stale projects by deal value and RAG. | O13: tbl_projects; tbl_project_executive_summary | P13: Available – KPI Rule Required | Q13: Predefined multi-table KPI / trend aggregation | R13: High | S13: Orbit KPI/Watchlist Tool with fixed formulas; cache intent/query plan, execute against live data; use Mesh only to explain computed results. | T13: Pending – Complex KPI SQL Design
... A15: New – Executive / KPI / Dashboard | C15: CEO / Strategy / Delivery Head | D15: High | E15: Executive Portfolio | F15: Trend / Dashboard KPI | G15: Complex | H15: quarterly_portfolio_flow | I15: What is the quarterly trend of projects started, due, completed, and overdue? | J15: Show portfolio inflow and delivery outcomes by quarter. | K15: Is the organisation taking on work faster than it completes it? | L15: start_date; end_date; completion_status_types | M15: Assess portfolio throughput and capacity pressure. | N15: Count projects by start_date, end_date, and configured completed status; calculate overdue projects at each quarter end. | O15: tbl_projects; tbl_project_status | P15: Available – KPI Rule Required | Q15: Predefined multi-table KPI / trend aggregation | R15: High | S15: Orbit KPI/Watchlist Tool with fixed formulas; cache intent/query plan, execute against live data; use Mesh only to explain computed results. | T15: Pending – Complex KPI SQL Design
A16: New – Executive / KPI / Dashboard | C16: CEO / Delivery Head / PMO | D16: High | E16: Executive Portfolio | F16: Exception / KPI | G16: Complex | H16: stage_aging | I16: Which projects have remained in the same delivery stage for too long? | J16: Show stage aging across active projects. | K16: Which projects appear stuck in their current stage? | L16: as_of_date; stage_age_thresholds | M16: Identify stalled projects while clearly exposing the data limitation. | N16: Use project_stage_id and update_date as an available proxy for stage aging; exact stage-entry age requires history and should be labelled approximate. | O16: tbl_projects; tbl_project_stages | P16: Available – KPI Rule Required | Q16: Predefined multi-table KPI / trend aggregation | R16: High | S16: Orbit KPI/Watchlist Tool with fixed formulas; cache intent/query plan, execute against live data; use Mesh only to explain computed results. | T16: Pending – Complex KPI SQL Design | V16: Approximate metric because project stage history is not populated.
A17: New – Executive / KPI / Dashboard | C17: CEO / Delivery Head / PMO | D17: High | E17: Delivery Health | F17: Exception / Diagnostic | G17: Complex | H17: active_projects_without_recent_activity | I17: Which active projects show no recent task, issue, risk, timesheet, or summary activity? | J17: Find active projects that appear dormant. | K17: Which projects have had no operational activity in the last :days days? | L17: days; as_of_date | M17: Detect abandoned, inaccurately active, or poorly maintained projects. | N17: Calculate the latest activity date across project update, task update, issue update, risk update/history, timesheet, and executive summary. | O17: tbl_projects; tbl_project_tasks; tbl_project_issues; tbl_risk; tbl_risk_history; tbl_timesheets; tbl_project_executive_summary | P17: Available – KPI Rule Required | Q17: Predefined multi-table KPI / trend aggregation | R17: High | S17: Orbit KPI/Watchlist Tool with fixed formulas; cache intent/query plan, execute against live data; use Mesh only to explain computed results. | T17: Pending – Complex KPI SQL Design
A18: New – Executive / KPI / Dashboard | C18: Delivery Head / PMO / PM | D18: High | E18: Delivery Health | F18: Exception / Diagnostic | G18: Complex | H18: project_end_before_open_task_due | I18: Which projects have open tasks due after the project end date? | J18: Show project schedules that are internally inconsistent. | K18: Which committed project dates are earlier than their remaining task deadlines? | L18: as_of_date | M18: Identify schedule-plan inconsistencies requiring rebaselining. | N18: Find active/open tasks where task.due_date > project.end_date; summarise count, latest due date, and high-priority exposure by project. | O18: tbl_projects; tbl_project_tasks; tbl_project_task_status | P18: Available – KPI Rule Required | Q18: Predefined multi-table KPI / trend aggregation | R18: High | S18: Orbit KPI/Watchlist Tool with fixed formulas; cache intent/query plan, execute against live data; use Mesh only to explain computed results. | T18: Pending – Complex KPI SQL Design
A19: New – Executive / KPI / Dashboard | C19: Delivery Head / PM / Team Lead | D19: High | E19: Tasks | F19: Executive Composite KPI | G19: Very Complex | H19: critical_bottleneck_tasks | I19: Which incomplete tasks are blocking the largest number of dependent tasks? | J19: Rank overdue bottleneck tasks by downstream dependency count. | K19: What tasks create the greatest delivery bottleneck? | L19: project_identifier; as_of_date; top_n | M19: Focus execution on blockers with the largest downstream impact. | N19: Count tasks whose dependent_task_id points to each incomplete task; combine downstream count, overdue days, priority, RAG, and assignee availability. | O19: tbl_project_tasks; tbl_project_task_status; tbl_project_task_users; tbl_projects | P19: Available – KPI Rule Required | Q19: Composite multi-table ranking | R19: High | S19: Orbit KPI/Watchlist Tool with fixed formulas; cache intent/query plan, execute against live data; use Mesh only to explain computed results. | T19: Pending – Complex KPI SQL Design
A20: New – Executive / KPI / Dashboard | C20: Delivery Head / Portfolio Head / PMO | D20: High | E20: Tasks | F20: Dashboard KPI | G20: Complex | H20: high_priority_backlog_concentration | I20: Which projects contain the highest concentration of open High-priority or Red-RAG tasks? | J20: Rank projects by critical task backlog. | K20: Where is urgent delivery work concentrated? | L20: as_of_date; top_n | M20: Prioritise portfolio recovery actions. | N20: Critical backlog ratio = open High-priority or configured Red-RAG tasks ÷ all open tasks; include count and overdue days. | O20: tbl_projects; tbl_project_tasks; tbl_project_task_status | P20: Available – KPI Rule Required | Q20: Predefined multi-table KPI / trend aggregation | R20: High | S20: Orbit KPI/Watchlist Tool with fixed formulas; cache intent/query plan, execute against live data; use Mesh only to explain computed results. | T20: Pending – Complex KPI SQL Design
A21: New – Executive / KPI / Dashboard | C21: PM / Team Lead / Delivery Head | D21: High | E21: Tasks | F21: Exception / KPI | G21: Complex | H21: tasks_due_soon_low_completion | I21: Which tasks are due within :days days but remain below :completion_percent complete? | J21: Show near-term tasks at risk of missing due dates. | K21: What upcoming work needs immediate action? | L21: days; completion_percent; as_of_date; optional_project | M21: Create a proactive short-term execution watchlist. | N21: Filter open tasks by due-date horizon and percent_complete threshold; rank by priority, RAG, estimate_complete, and dependency impact. | O21: tbl_project_tasks; tbl_project_task_status; tbl_projects | P21: Available – KPI Rule Required | Q21: Predefined multi-table KPI / trend aggregation | R21: High | S21: Orbit KPI/Watchlist Tool with fixed formulas; cache intent/query plan, execute against live data; use Mesh only to explain computed results. | T21: Pending – Complex KPI SQL Design
A22: New – Executive / KPI / Dashboard | C22: Delivery Head / PMO / Finance | D22: High | E22: Tasks | F22: KPI / Comparative | G22: Complex | H22: portfolio_task_estimate_variance | I22: Which projects and tasks have the largest estimate-to-actual effort variance? | J22: Rank task overruns across the portfolio. | K22: Where are estimates least accurate? | L22: period; top_n; actual_effort_source | M22: Improve estimation quality and identify overruns. | N22: Compare task estimate with live timesheet hours; aggregate variance and variance percentage by task, project, PM, type, and client. | O22: tbl_project_tasks; tbl_timesheets; tbl_projects; tbl_users; tbl_clients | P22: Available – KPI Rule Required | Q22: Predefined multi-table KPI / trend aggregation | R22: High | S22: Orbit KPI/Watchlist Tool with fixed formulas; cache intent/query plan, execute against live data; use Mesh only to explain computed results. | T22: Pending – Complex KPI SQL Design
A23: New – Executive / KPI / Dashboard | C23: Delivery Head / PMO / PM | D23: High | E23: Tasks | F23: Exception / KPI | G23: Complex | H23: task_completion_timesheet_mismatch | I23: Which tasks show high completion percentages but little or no recent time logged, or heavy time logged with low completion? | J23: Find task progress and effort inconsistencies. | K23: Where does reported completion conflict with timesheet evidence? | L23: period; completion_thresholds; hours_thresholds | M23: Detect inaccurate progress reporting and hidden blockers. | N23: Compare task.percent_complete with timesheet hours during the selected period and task estimate; flag both mismatch directions. | O23: tbl_project_tasks; tbl_timesheets; tbl_projects | P23: Available – KPI Rule Required | Q23: Predefined multi-table KPI / trend aggregation | R23: High | S23: Orbit KPI/Watchlist Tool with fixed formulas; cache intent/query plan, execute against live data; use Mesh only to explain computed results. | T23: Pending – Complex KPI SQL Design
A24: New – Executive / KPI / Dashboard | C24: CEO / Delivery Head / PMO | D24: High | E24: Delivery Health | F24: Executive Composite KPI | G24: Very Complex | H24: project_task_rag_mismatch | I24: Which projects have a Green project RAG but a significant Red-task backlog? | J24: Find mismatches between project health and task-level health. | K24: Where may project RAG be understating delivery risk? | L24: red_task_ratio_threshold; as_of_date | M24: Detect optimistic project-level reporting. | N24: Compare project.rag with count/ratio of open task.rag values and overdue High-priority tasks. | O24: tbl_projects; tbl_project_tasks; tbl_project_task_status | P24: Available – KPI Rule Required | Q24: Composite multi-table ranking | R24: High | S24: Orbit KPI/Watchlist Tool with fixed formulas; cache intent/query plan, execute against live data; use Mesh only to explain computed results. | T24: Pending – Complex KPI SQL Design
A25: New – Executive / KPI / Dashboard | C25: Delivery Head / Resource Manager / PMO | D25: High | E25: Tasks | F25: Dashboard KPI | G25: Complex | H25: unassigned_task_ratio | I25: Which projects have the highest percentage of open tasks without active assignees? | J25: Rank projects by unassigned work. | K25: Where is delivery work not owned? | L25: as_of_date; minimum_open_tasks | M25: Identify execution ownership gaps. | N25: Open tasks without an active row in tbl_project_task_users ÷ total open tasks, grouped by project and PM. | O25: tbl_projects; tbl_project_tasks; tbl_project_task_status; tbl_project_task_users; tbl_users | P25: Available – KPI Rule Required | Q25: Predefined multi-table KPI / trend aggregation | R25: High | S25: Orbit KPI/Watchlist Tool with fixed formulas; cache intent/query plan, execute against live data; use Mesh only to explain computed results. | T25: Pending – Complex KPI SQL Design
A26: New – Executive / KPI / Dashboard | C26: Delivery Head / Quality / PMO | D26: High | E26: Governance | F26: Dashboard KPI | G26: Complex | H26: acceptance_criteria_completeness | I26: Which active projects have the lowest acceptance-criteria coverage on open tasks? | J26: Show projects with incomplete task acceptance criteria. | K26: Where is scope validation weak? | L26: as_of_date; minimum_task_count | M26: Improve delivery quality and reduce ambiguity. | N26: Percentage of active/open tasks with non-empty acceptance_criteria; rank low-coverage projects and include deal value/RAG. | O26: tbl_projects; tbl_project_tasks; tbl_project_task_status | P26: Available – KPI Rule Required | Q26: Predefined multi-table KPI / trend aggregation | R26: High | S26: Orbit KPI/Watchlist Tool with fixed formulas; cache intent/query plan, execute against live data; use Mesh only to explain computed results. | T26: Pending – Complex KPI SQL Design
A27: New – Executive / KPI / Dashboard | C27: CEO / Delivery Head / Quality | D27: High | E27: Issues | F27: Trend / Dashboard KPI | G27: Complex | H27: issue_backlog_trend | I27: Is the issue backlog increasing or decreasing by project over the last :months months? | J27: Show issue creation versus closure trend. | K27: Which projects are accumulating issues faster than they close them? | L27: months; time_bucket | M27: Detect deteriorating quality before it affects delivery. | N27: For each period, count issues raised and closed using date_raised/date_closed; calculate net backlog change and rolling closure ratio. | O27: tbl_projects; tbl_project_issues; tbl_project_issue_status | P27: Available – KPI Rule Required | Q27: Predefined multi-table KPI / trend aggregation | R27: High | S27: Orbit KPI/Watchlist Tool with fixed formulas; cache intent/query plan, execute against live data; use Mesh only to explain computed results. | T27: Pending – Complex KPI SQL Design
A28: New – Executive / KPI / Dashboard | C28: Delivery Head / Quality / PMO | D28: High | E28: Issues | F28: KPI / Comparative | G28: Complex | H28: issue_aging_closure_performance | I28: Which projects have the oldest unresolved issues and the slowest closure performance? | J28: Rank projects by issue aging and time to close. | K28: Where is issue resolution performance weakest? | L28: as_of_date; period; minimum_issue_count | M28: Prioritise issue-resolution process improvements. | N28: Open age = as_of_date - date_raised. Closed cycle time = date_closed - date_raised. Summarise median/average, overdue ratio, and closure rate. | O28: tbl_projects; tbl_project_issues; tbl_project_issue_status | P28: Available – KPI Rule Required | Q28: Predefined multi-table KPI / trend aggregation | R28: High | S28: Orbit KPI/Watchlist Tool with fixed formulas; cache intent/query plan, execute against live data; use Mesh only to explain computed results. | T28: Pending – Complex KPI SQL Design
... A45: New – Executive / KPI / Dashboard | C45: CEO / Executive Committee | D45: High | E45: Executive Portfolio | F45: Forecast / Predictive | G45: Very Complex | H45: executive_30_60_90_day_watchlist | I45: What projects, risks, tasks, issues, and allocation expiries need executive attention in the next 30, 60, and 90 days? | J45: Create a 30/60/90-day delivery watchlist. | K45: What upcoming events could materially affect the portfolio? | L45: as_of_date; scoring_weights; horizons | M45: Provide a single forward-looking executive action agenda. | N45: Create horizon buckets using project end dates, task due dates, issue planned closure dates, risk target/revised closure dates, and allocation_to dates; rank by deal value, RAG, severity/exposure, and dependency. | O45: tbl_projects; tbl_project_tasks; tbl_project_issues; tbl_risk; tbl_project_users; tbl_users | P45: Available – KPI Rule Required | Q45: Deterministic forecast / watchlist scoring | R45: High | S45: Orbit KPI/Watchlist Tool with fixed formulas; cache intent/query plan, execute against live data; use Mesh only to explain computed results. | T45: Pending – Complex KPI SQL Design

Sheet Deferred Empty Tables
A1: Original ID | B1: PMS Area | C1: Canonical Intent | D1: Primary Question | E1: Empty Tables | F1: Reason | G1: Recommended Replacement | H1: Original Mapping Status
A2: 13 | B2: Projects | C2: projects_by_team | D2: Show projects for team :team_name. | E2: tbl_project_team | F2: Dead — Team Not Populated | G2: Use project/resource allocation questions; team-name reporting is unavailable because tbl_project_team is empty. | H2: Mapped – Direct Schema
A3: 21 | B3: Milestones | C3: project_milestones | D3: Show milestones for :project_name. | E3: tbl_project_task_milestone, tbl_project_task_milestone_mapping | F3: Dead — Milestone Module Unused | G3: Use task due-date, dependency, and delivery-risk questions until milestone data is populated. | H3: Mapped – Direct Schema
A4: 22 | B4: Milestones | C4: upcoming_milestones | D4: Which milestones are due in the next :days days? | E4: tbl_project_task_milestone, tbl_project_task_milestone_mapping | F4: Dead — Milestone Module Unused | G4: Use task due-date, dependency, and delivery-risk questions until milestone data is populated. | H4: Mapped – Direct Schema
A5: 23 | B5: Milestones | C5: overdue_milestones | D5: Which milestones are overdue? | E5: tbl_project_task_milestone | F5: Blocked — No Data + Business Rule | G5: Use task due-date, dependency, and delivery-risk questions until milestone data is populated. | H5: Not Applicable – Non-Direct Support
A6: 24 | B6: Milestones | C6: next_project_milestone | D6: What is the next milestone for :project_name? | E6: tbl_project_task_milestone, tbl_project_task_milestone_mapping | F6: Dead — Milestone Module Unused | G6: Use task due-date, dependency, and delivery-risk questions until milestone data is populated. | H6: Mapped – Direct Schema
A7: 25 | B7: Milestones | C7: milestone_tasks | D7: Which tasks belong to milestone :milestone_name? | E7: tbl_project_task_milestone, tbl_project_task_milestone_mapping | F7: Dead — Milestone Module Unused | G7: Use task due-date, dependency, and delivery-risk questions until milestone data is populated. | H7: Mapped – Direct Schema
A8: 27 | B8: Milestones | C8: milestones_without_tasks | D8: Which milestones have no mapped tasks? | E8: tbl_project_task_milestone, tbl_project_task_milestone_mapping | F8: Dead — Milestone Module Unused | G8: Use task due-date, dependency, and delivery-risk questions until milestone data is populated. | H8: Mapped – Direct Schema
A9: 29 | B9: Milestones | C9: milestones_due_month | D9: Which milestones are due this month? | E9: tbl_project_task_milestone, tbl_project_task_milestone_mapping | F9: Dead — Milestone Module Unused | G9: Use task due-date, dependency, and delivery-risk questions until milestone data is populated. | H9: Mapped – Direct Schema
A10: 72 | B10: Resources | C10: resources_by_team | D10: Show active users in team :team_name. | E10: tbl_project_team | F10: Blocked — No Data + Business Rule | G10: Use project/resource allocation questions; team-name reporting is unavailable because tbl_project_team is empty. | H10: Not Applicable – Non-Direct Support
A11: 93 | B11: Estimation & Financials | C11: project_estimation_versions | D11: Show estimation versions for :project_name. | E11: tbl_project_estimation | F11: Dead — Estimation Module Unused | G11: Use project-level estimate, booked hours, chargeable hours, grant hours, and deal value until estimation tables are populated. | H11: Mapped – Direct Schema
A12: 94 | B12: Estimation & Financials | C12: project_estimation_status | D12: What is the estimation status for :project_name? | E12: tbl_project_estimation | F12: Dead — Estimation Module Unused | G12: Use project-level estimate, booked hours, chargeable hours, grant hours, and deal value until estimation tables are populated. | H12: Mapped – Direct Schema
A13: 95 | B13: Estimation & Financials | C13: estimation_summary | D13: Show the detailed estimation summary for :project_name. | E13: tbl_estimation_summary, tbl_project_estimation | F13: Dead — Estimation Module Unused | G13: Use project-level estimate, booked hours, chargeable hours, grant hours, and deal value until estimation tables are populated. | H13: Mapped – Direct Schema
... A15: 97 | B15: Estimation & Financials | C15: estimation_risks | D15: Show estimation risks for :project_name. | E15: tbl_estimation_risks, tbl_project_estimation | F15: Dead — Estimation Module Unused | G15: Use project-level estimate, booked hours, chargeable hours, grant hours, and deal value until estimation tables are populated. | H15: Mapped – Direct Schema

Sheet Data Coverage
A1: Table | B1: Data Status | C1: Question Usage Count | D1: Use in Reorganized Catalogue | E1: Notes
A2: tbl_projects | B2: Populated / not listed as empty | C2: =COUNTIF('Reorganized Questionnaire'!O:O,"*tbl_projects*") | D2: Yes | E2: Used for simple or complex questions in the active catalogue.
A3: tbl_project_status | B3: Populated / not listed as empty | C3: =COUNTIF('Reorganized Questionnaire'!O:O,"*tbl_project_status*") | D3: Yes | E3: Used for simple or complex questions in the active catalogue.
A4: tbl_project_stages | B4: Populated / not listed as empty | C4: =COUNTIF('Reorganized Questionnaire'!O:O,"*tbl_project_stages*") | D4: Yes | E4: Used for simple or complex questions in the active catalogue.
A5: tbl_project_types | B5: Populated / not listed as empty | C5: =COUNTIF('Reorganized Questionnaire'!O:O,"*tbl_project_types*") | D5: Yes | E5: Used for simple or complex questions in the active catalogue.
A6: tbl_clients | B6: Populated / not listed as empty | C6: =COUNTIF('Reorganized Questionnaire'!O:O,"*tbl_clients*") | D6: Yes | E6: Used for simple or complex questions in the active catalogue.
A7: department | B7: Populated / not listed as empty | C7: =COUNTIF('Reorganized Questionnaire'!O:O,"*department*") | D7: Yes | E7: Used for simple or complex questions in the active catalogue.
A8: tbl_project_tasks | B8: Populated / not listed as empty | C8: =COUNTIF('Reorganized Questionnaire'!O:O,"*tbl_project_tasks*") | D8: Yes | E8: Used for simple or complex questions in the active catalogue.
A9: tbl_project_task_status | B9: Populated / not listed as empty | C9: =COUNTIF('Reorganized Questionnaire'!O:O,"*tbl_project_task_status*") | D9: Yes | E9: Used for simple or complex questions in the active catalogue.
A10: tbl_project_task_users | B10: Populated / not listed as empty | C10: =COUNTIF('Reorganized Questionnaire'!O:O,"*tbl_project_task_users*") | D10: Yes | E10: Used for simple or complex questions in the active catalogue.
A11: tbl_timesheets | B11: Populated / not listed as empty | C11: =COUNTIF('Reorganized Questionnaire'!O:O,"*tbl_timesheets*") | D11: Yes | E11: Used for simple or complex questions in the active catalogue.
A12: tbl_project_users | B12: Populated / not listed as empty | C12: =COUNTIF('Reorganized Questionnaire'!O:O,"*tbl_project_users*") | D12: Yes | E12: Used for simple or complex questions in the active catalogue.
A13: tbl_users | B13: Populated / not listed as empty | C13: =COUNTIF('Reorganized Questionnaire'!O:O,"*tbl_users*") | D13: Yes | E13: Used for simple or complex questions in the active catalogue.
A14: tbl_project_issues | B14: Populated / not listed as empty | C14: =COUNTIF('Reorganized Questionnaire'!O:O,"*tbl_project_issues*") | D14: Yes | E14: Used for simple or complex questions in the active catalogue.
A15: tbl_project_issue_status | B15: Populated / not listed as empty | C15: =COUNTIF('Reorganized Questionnaire'!O:O,"*tbl_project_issue_status*") | D15: Yes | E15: Used for simple or complex questions in the active catalogue.
A16: tbl_project_issue_users | B16: Populated / not listed as empty | C16: =COUNTIF('Reorganized Questionnaire'!O:O,"*tbl_project_issue_users*") | D16: Yes | E16: Used for simple or complex questions in the active catalogue.
A17: tbl_risk | B17: Populated / not listed as empty | C17: =COUNTIF('Reorganized Questionnaire'!O:O,"*tbl_risk*") | D17: Yes | E17: Used for simple or complex questions in the active catalogue.
A18: tbl_risk_status | B18: Populated / not listed as empty | C18: =COUNTIF('Reorganized Questionnaire'!O:O,"*tbl_risk_status*") | D18: Yes | E18: Used for simple or complex questions in the active catalogue.
A19: tbl_risk_probability | B19: Populated / not listed as empty | C19: =COUNTIF('Reorganized Questionnaire'!O:O,"*tbl_risk_probability*") | D19: Yes | E19: Used for simple or complex questions in the active catalogue.
A20: tbl_risk_impact | B20: Populated / not listed as empty | C20: =COUNTIF('Reorganized Questionnaire'!O:O,"*tbl_risk_impact*") | D20: Yes | E20: Used for simple or complex questions in the active catalogue.
A21: tbl_risk_priority | B21: Populated / not listed as empty | C21: =COUNTIF('Reorganized Questionnaire'!O:O,"*tbl_risk_priority*") | D21: Yes | E21: Used for simple or complex questions in the active catalogue.
A22: tbl_risk_history | B22: Populated / not listed as empty | C22: =COUNTIF('Reorganized Questionnaire'!O:O,"*tbl_risk_history*") | D22: Yes | E22: Used for simple or complex questions in the active catalogue.
A23: tbl_project_executive_summary | B23: Populated / not listed as empty | C23: =COUNTIF('Reorganized Questionnaire'!O:O,"*tbl_project_executive_summary*") | D23: Yes | E23: Used for simple or complex questions in the active catalogue.
A24: tbl_project_users_log | B24: Populated / not listed as empty | C24: =COUNTIF('Reorganized Questionnaire'!O:O,"*tbl_project_users_log*") | D24: Yes | E24: Used for simple or complex questions in the active catalogue.
A26: PMS tables currently empty and excluded/deferred
A27: tbl_estimation_asumption | B27: Empty | C27: 1 | D27: No, unless a populated alternative exists | E27: Blocks 1 mapped SQL queries (0 rows)
A28: tbl_estimation_deliverables | B28: Empty | C28: 0 | D28: No, unless a populated alternative exists | E28: PMS table — not referenced in questionnaire
A29: tbl_estimation_risks | B29: Empty | C29: 1 | D29: No, unless a populated alternative exists | E29: Blocks 1 mapped SQL queries (0 rows)
A30: tbl_estimation_summary | B30: Empty | C30: 1 | D30: No, unless a populated alternative exists | E30: Blocks 1 mapped SQL queries (0 rows)
A31: tbl_group_task_income_var | B31: Empty | C31: 0 | D31: No, unless a populated alternative exists | E31: PMS table — not referenced in questionnaire
A32: tbl_process_issue_analysis | B32: Empty | C32: 0 | D32: No, unless a populated alternative exists | E32: PMS table — not referenced in questionnaire
A33: tbl_project_department | B33: Empty | C33: 1 | D33: No, unless a populated alternative exists | E33: Blocks 1 mapped SQL queries (0 rows)
A34: tbl_project_documents | B34: Empty | C34: 0 | D34: No, unless a populated alternative exists | E34: PMS table — not referenced in questionnaire
A35: tbl_project_estimation | B35: Empty | C35: 5 | D35: No, unless a populated alternative exists | E35: Blocks 5 mapped SQL queries (0 rows)
A36: tbl_project_estimation_audit_trails | B36: Empty | C36: 0 | D36: No, unless a populated alternative exists | E36: PMS table — not referenced in questionnaire
A37: tbl_project_estimation_lineitem_map | B37: Empty | C37: 0 | D37: No, unless a populated alternative exists | E37: PMS table — not referenced in questionnaire
A38: tbl_project_initiation_records | B38: Empty | C38: 0 | D38: No, unless a populated alternative exists | E38: PMS table — not referenced in questionnaire
... A59: temp_all_task | B59: Empty | C59: 0 | D59: No, unless a populated alternative exists | E59: PMS table — not referenced in questionnaire

Sheet QUESTION + QUERY
A1: S.No | B1: PMS Area | C1: Canonical Intent | D1: Primary Question | E1: Alternative Phrasing 1 | F1: Alternative Phrasing 2 | G1: Required Entities / Parameters | H1: Schema Support | I1: Relevant Schema Objects | J1: Query Mapping Status | K1: Clarification / Mapping Notes | L1: SQL Query (MySQL Template) | M1: SQL VERIFIED STATUS (PMS DB) | N1: SQL Mapping Result | O1: Comment | P1: Empty Tables Referenced | Q1: Data Availability | R1: NL2SQL Readiness
A2: 1 | B2: Projects | C2: my_active_projects | D2: What are my active projects? | E2: Show the projects I am currently working on. | F2: List my ongoing projects. | G2: current_user | H2: Direct | I2: tbl_projects; tbl_project_users | J2: Not Mapped – Business Rule Required | K2: Define whether “my” includes member, PM, owner, or task assignee. | L2: SELECT DISTINCT p.project_id, p.project_unique_id, p.project_key, p.title, p.start_date, p.end_date, ps.status_name, st.stage_name, p.priority, p.rag FROM tbl_projects p JOIN tbl_project_users pu ON p.project_id = pu.project_id LEFT JOIN tbl_project_status ps ON ps.status_id = p.project_status_id LEFT JOIN tbl_project_stages st ON st.stage_id = p.project_stage_id WHERE pu.user_id = 3066 AND pu.request_status = 'A' AND pu.status = 1 AND p.status = 1 AND p.archive = 0 ORDER BY p.title ASC | M2: Verified | N2: Not mapped: “my” and “active” scope are not defined (member, PM, owner, assignee; accepted/current-date/status filters). | P2: — | Q2: N/A | R2: Blocked — Business Rule / Schema Gap
A3: 2 | B3: Projects | C3: projects_managed_by_me | D3: Which projects am I managing? | E3: Show projects where I am the project manager. | F3: List projects managed by me. | G3: current_user | H3: Direct | I3: tbl_projects.pm_user_id | J3: Mapped – Direct Schema | K3: Use PM field; confirm whether project_owner_id also counts. | L3: SELECT p.project_id, p.project_unique_id, p.project_key, p.title, p.start_date, p.end_date, ps.status_name, st.stage_name, p.priority, p.rag FROM tbl_projects p LEFT JOIN tbl_project_status ps ON ps.status_id = p.project_status_id LEFT JOIN tbl_project_stages st ON st.stage_id = p.project_stage_id WHERE p.pm_user_id = :current_user_id AND p.status = 1 AND p.archive = 0 ORDER BY p.end_date, p.title; | M3: Pending | N3: Mapped from schema | P3: — | Q3: Data Available | R3: Ready for Verification
A4: 3 | B4: Projects | C4: projects_owned_by_me | D4: Which projects do I own? | E4: Show projects where I am the owner. | F4: List projects owned by me. | G4: current_user | H4: Direct | I4: tbl_projects.project_owner_id | J4: Mapped – Direct Schema | K4: Distinct from project manager. | L4: SELECT p.project_id, p.project_unique_id, p.project_key, p.title, p.start_date, p.end_date, ps.status_name, st.stage_name, p.priority, p.rag FROM tbl_projects p LEFT JOIN tbl_project_status ps ON ps.status_id = p.project_status_id LEFT JOIN tbl_project_stages st ON st.stage_id = p.project_stage_id WHERE p.project_owner_id = :current_user_id AND p.status = 1 AND p.archive = 0 ORDER BY p.end_date, p.title; | M4: Pending | N4: Mapped from schema | P4: — | Q4: Data Available | R4: Ready for Verification
A5: 4 | B5: Projects | C5: project_details | D5: Show details of project :project_name. | E5: Give me the project information for :project_name. | F5: Open the summary of :project_name. | G5: project_name | H5: Direct | I5: tbl_projects | J5: Not Mapped – Schema Ambiguous | K5: Project-name matching and duplicate-title handling required. | M5: Pending | N5: Not mapped: project title may not be unique; preferred identifier must be confirmed. | O5: tbl_projects.project_unique_id Instead of project name it may ask the PF Id | P5: — | Q5: N/A | R5: Blocked — Business Rule / Schema Gap
A6: 5 | B6: Projects | C6: project_status | D6: What is the status of project :project_name? | E6: Show the current status of :project_name. | F6: Is :project_name active or completed? | G6: project_name | H6: Direct | I6: tbl_projects; tbl_project_status | J6: Mapped – Direct Schema | K6: Lookup master data required. | L6: SELECT p.project_id, p.project_key, p.title, p.project_status_id, ps.status_name, ps.color_code FROM tbl_projects p LEFT JOIN tbl_project_status ps ON ps.status_id = p.project_status_id WHERE p.title = :project_name AND p.status = 1 AND p.archive = 0 ORDER BY p.project_id; | M6: Pending | N6: Mapped from schema | P6: — | Q6: Data Available | R6: Ready for Verification
A7: 6 | B7: Projects | C7: project_stage | D7: What stage is :project_name in? | E7: Show the current stage of :project_name. | F7: Which delivery stage has :project_name reached? | G7: project_name | H7: Direct | I7: tbl_projects; tbl_project_stages | J7: Mapped – Direct Schema | K7: Lookup master data required. | L7: SELECT p.project_id, p.project_key, p.title, p.project_stage_id, st.stage_name, st.color_code FROM tbl_projects p LEFT JOIN tbl_project_stages st ON st.stage_id = p.project_stage_id WHERE p.title = :project_name AND p.status = 1 AND p.archive = 0 ORDER BY p.project_id; | M7: Pending | N7: Mapped from schema | P7: — | Q7: Data Available | R7: Ready for Verification
A8: 7 | B8: Projects | C8: project_rag | D8: What is the RAG status of :project_name? | E8: Show the health colour of :project_name. | F8: Is :project_name red, amber, or green? | G8: project_name | H8: Direct | I8: tbl_projects.rag | J8: Mapped – Direct Schema | K8: Confirm stored values and meaning. | L8: SELECT p.project_id, p.project_key, p.title, p.rag FROM tbl_projects p WHERE p.title = :project_name AND p.status = 1 AND p.archive = 0 ORDER BY p.project_id; | M8: Pending | N8: Mapped from schema | P8: — | Q8: Data Available | R8: Ready for Verification
A9: 8 | B9: Projects | C9: project_priority | D9: What is the priority of :project_name? | E9: Show the priority assigned to :project_name. | F9: Is :project_name high priority? | G9: project_name | H9: Direct | I9: tbl_projects.priority; tbl_project_priority | J9: Mapped – Direct Schema | K9: Confirm whether priority stores ID or text. | L9: SELECT p.project_id, p.project_key, p.title, p.priority AS priority_id, pp.priority_name, pp.priority_order FROM tbl_projects p LEFT JOIN tbl_project_priority pp ON pp.priority_id = p.priority WHERE p.title = :project_name AND p.status = 1 AND p.archive = 0 ORDER BY p.project_id; | M9: Pending | N9: Mapped from schema | P9: tbl_project_priority | Q9: Partial (Lookup Empty) | R9: Degraded — Priority Label NULL
A10: 9 | B10: Projects | C10: projects_starting_period | D10: Which projects start between :start_date and :end_date? | E10: Show projects beginning in the selected period. | F10: List upcoming project starts. | G10: start_date, end_date | H10: Direct | I10: tbl_projects.start_date | J10: Mapped – Direct Schema | K10: Date boundaries to be inclusive. | L10: SELECT p.project_id, p.project_key, p.title, p.start_date, p.end_date, ps.status_name, p.rag FROM tbl_projects p LEFT JOIN tbl_project_status ps ON ps.status_id = p.project_status_id WHERE p.start_date >= :start_date AND p.start_date < DATE_ADD(:end_date, INTERVAL 1 DAY) AND p.status = 1 AND p.archive = 0 ORDER BY p.start_date, p.title; | M10: Pending | N10: Mapped from schema | P10: — | Q10: Data Available | R10: Ready for Verification
A11: 10 | B11: Projects | C11: projects_ending_period | D11: Which projects end between :start_date and :end_date? | E11: Show projects scheduled to finish in the selected period. | F11: List upcoming project end dates. | G11: start_date, end_date | H11: Direct | I11: tbl_projects.end_date | J11: Mapped – Direct Schema | K11: Date boundaries to be inclusive. | L11: SELECT p.project_id, p.project_key, p.title, p.start_date, p.end_date, ps.status_name, p.rag FROM tbl_projects p LEFT JOIN tbl_project_status ps ON ps.status_id = p.project_status_id WHERE p.end_date >= :start_date AND p.end_date < DATE_ADD(:end_date, INTERVAL 1 DAY) AND p.status = 1 AND p.archive = 0 ORDER BY p.end_date, p.title; | M11: Pending | N11: Mapped from schema | P11: — | Q11: Data Available | R11: Ready for Verification
A12: 11 | B12: Projects | C12: overdue_projects | D12: Which projects are overdue? | E12: Show active projects past their end date. | F12: List delayed projects. | G12: as_of_date | H12: Derived | I12: tbl_projects.end_date; tbl_project_status | J12: Not Applicable – Non-Direct Support | K12: Define which project statuses are considered open. | M12: Pending | N12: Not applicable: schema support is not Direct. | O12: If tbl_projects.status==1 | P12: — | Q12: N/A | R12: Blocked — Business Rule / Schema Gap
A13: 12 | B13: Projects | C13: projects_by_department | D13: Show projects for department :department_name. | E13: List active projects owned by :department_name. | F13: Which projects belong to :department_name? | G13: department_name | H13: Direct | I13: tbl_projects.department_id; tbl_project_department | J13: Mapped – Direct Schema | K13: Confirm active-only default. | L13: SELECT p.project_id, p.project_key, p.title, d.department_name, ps.status_name, p.start_date, p.end_date FROM tbl_projects p JOIN tbl_project_department d ON d.department_id = p.department_id LEFT JOIN tbl_project_status ps ON ps.status_id = p.project_status_id WHERE d.department_name = :department_name AND p.status = 1 AND p.archive = 0 ORDER BY p.title; | M13: Pending | N13: Mapped from schema | P13: tbl_project_department | Q13: No Data (Table Empty) | R13: Dead — Department Not Populated
A14: 13 | B14: Projects | C14: projects_by_team | D14: Show projects for team :team_name. | E14: List projects assigned to :team_name. | F14: Which projects belong to :team_name? | G14: team_name | H14: Direct | I14: tbl_projects.team_id; tbl_project_team | J14: Mapped – Direct Schema | K14: Confirm team hierarchy handling. | L14: SELECT p.project_id, p.project_key, p.title, t.team_name, ps.status_name, p.start_date, p.end_date FROM tbl_projects p JOIN tbl_project_team t ON t.team_id = p.team_id LEFT JOIN tbl_project_status ps ON ps.status_id = p.project_status_id WHERE t.team_name = :team_name AND p.status = 1 AND p.archive = 0 ORDER BY p.title; | M14: Pending | N14: Mapped from schema | P14: tbl_project_team | Q14: No Data (Table Empty) | R14: Dead — Team Not Populated
A15: 14 | B15: Projects | C15: projects_by_type | D15: Show projects of type :project_type. | E15: List :project_type projects. | F15: Which projects use project type :project_type? | G15: project_type | H15: Direct | I15: tbl_projects.project_type_id; tbl_project_types | J15: Mapped – Direct Schema | K15: Lookup values required. | L15: SELECT p.project_id, p.project_key, p.title, pt.project_type, ps.status_name, p.start_date, p.end_date FROM tbl_projects p JOIN tbl_project_types pt ON pt.project_type_id = p.project_type_id LEFT JOIN tbl_project_status ps ON ps.status_id = p.project_status_id WHERE pt.project_type = :project_type AND p.status = 1 AND p.archive = 0 ORDER BY p.title; | M15: Pending | N15: Mapped from schema | P15: — | Q15: Data Available | R15: Ready for Verification
A16: 15 | B16: Projects | C16: projects_by_client | D16: Show projects for client :client_name. | E16: List projects associated with :client_name. | F16: Which projects belong to :client_name? | G16: client_name | H16: Partial | I16: tbl_projects.client_id | J16: Not Applicable – Non-Direct Support | K16: Client master table must be confirmed. | M16: Pending | N16: Not applicable: schema support is not Direct. | O16: tbl_projects.client_id=tbl_clients.id | P16: — | Q16: N/A | R16: Blocked — Business Rule / Schema Gap
A17: 16 | B17: Projects | C17: project_team_size | D17: How many active users are allocated to :project_name? | E17: Show the team size of :project_name. | F17: How many people are on :project_name? | G17: project_name | H17: Direct | I17: tbl_project_users | J17: Not Mapped – Business Rule Required | K17: Define active allocation and request_status filters. | M17: Pending | N17: Not mapped: active allocation and request-status/date rules need confirmation. | O17: tbl_project_users.status=1 | P17: — | Q17: N/A | R17: Blocked — Business Rule / Schema Gap
A18: 17 | B18: Projects | C18: projects_without_pm | D18: Which projects do not have a project manager? | E18: Show projects with no PM assigned. | F18: List unowned PM assignments. | G18: none | H18: Direct | I18: tbl_projects.pm_user_id | J18: Mapped – Direct Schema | K18: Null and zero handling required. | L18: SELECT p.project_id, p.project_key, p.title, p.start_date, p.end_date, ps.status_name FROM tbl_projects p LEFT JOIN tbl_project_status ps ON ps.status_id = p.project_status_id WHERE p.pm_user_id IS NULL AND p.status = 1 AND p.archive = 0 ORDER BY p.title; | M18: Pending | N18: Mapped from schema | P18: — | Q18: Data Available | R18: Ready for Verification
A19: 18 | B19: Projects | C19: projects_without_members | D19: Which active projects have no allocated users? | E19: Show projects without team members. | F19: List active projects with an empty team. | G19: none | H19: Derived | I19: tbl_projects; tbl_project_users | J19: Not Applicable – Non-Direct Support | K19: Define active project and active membership. | M19: Pending | N19: Not applicable: schema support is not Direct. | O19: If you want to exclude the PM/owner (ADMIN) from the member count — i.e., projects that have no PARTICIPANT members even if an ADMIN exists: SELECT p.project_id, p.title, p.short_url, p.status, p.post_date FROM tbl_projects p LEFT JOIN tbl_project_user pu ON p.project_id = pu.project_id AND pu.status = 1 AND pu.request_status = 'A' AND pu.access_type != 'ADMIN' WHERE p.status = 1 AND pu.project_id IS NULL ORDER BY p.title ASC | P19: — | Q19: N/A | R19: Blocked — Business Rule / Schema Gap
A20: 19 | B20: Projects | C20: project_recent_changes | D20: What changed recently in :project_name? | E20: Show recent project updates for :project_name. | F20: List recent status changes for :project_name. | G20: project_name, lookback_days | H20: Partial | I20: tbl_project_status_history; tbl_project_users_log; audit tables | J20: Not Applicable – Non-Direct Support | K20: Clarify which audit sources count as project changes. | M20: Pending | N20: Not applicable: schema support is not Direct. | P20: tbl_project_status_history | Q20: No Data (Table Empty) | R20: Blocked — No Data + Business Rule
A21: 20 | B21: Projects | C21: active_project_portfolio | D21: Give me a summary of active projects. | E21: Show active project counts by status and stage. | F21: Summarize the current project portfolio. | G21: current_user_scope | H21: Derived | I21: tbl_projects; status/stage masters | J21: Not Applicable – Non-Direct Support | K21: Define visibility scope and summary measures. | M21: Pending | N21: Not applicable: schema support is not Direct. | P21: — | Q21: N/A | R21: Blocked — Business Rule / Schema Gap
A22: 21 | B22: Milestones | C22: project_milestones | D22: Show milestones for :project_name. | E22: List all milestones mapped to :project_name. | F22: What milestones exist for :project_name? | G22: project_name | H22: Direct | I22: tbl_project_task_milestone; tbl_project_task_milestone_mapping | J22: Mapped – Direct Schema | K22: Milestones are inferred through mapping table. | L22: SELECT DISTINCT m.milestone_id, m.milestone, m.start_date, m.end_date FROM tbl_project_task_milestone m JOIN tbl_project_task_milestone_mapping mm ON mm.milestone_id = m.milestone_id JOIN tbl_projects p ON p.project_id = mm.project_id WHERE p.title = :project_name ORDER BY m.end_date, m.milestone; | M22: Pending | N22: Mapped from schema | P22: tbl_project_task_milestone, tbl_project_task_milestone_mapping | Q22: No Data (Table Empty) | R22: Dead — Milestone Module Unused
A23: 22 | B23: Milestones | C23: upcoming_milestones | D23: Which milestones are due in the next :days days? | E23: Show upcoming milestone deadlines. | F23: List milestones ending soon. | G23: days | H23: Direct | I23: tbl_project_task_milestone.end_date | J23: Mapped – Direct Schema | K23: Confirm whether mapping dates override milestone dates. | L23: SELECT DISTINCT p.project_id, p.project_key, p.title AS project_title, m.milestone_id, m.milestone, m.start_date, m.end_date FROM tbl_project_task_milestone m JOIN tbl_project_task_milestone_mapping mm ON mm.milestone_id = m.milestone_id JOIN tbl_projects p ON p.project_id = mm.project_id WHERE m.end_date >= CURRENT_DATE AND m.end_date < DATE_ADD(CURRENT_DATE, INTERVAL :days + 1 DAY) AND p.status = 1 AND p.archive = 0 ORDER BY m.end_date, p.title; | M23: Pending | N23: Mapped from schema | P23: tbl_project_task_milestone, tbl_project_task_milestone_mapping | Q23: No Data (Table Empty) | R23: Dead — Milestone Module Unused
A24: 23 | B24: Milestones | C24: overdue_milestones | D24: Which milestones are overdue? | E24: Show milestones past their end date. | F24: List delayed milestones. | G24: as_of_date | H24: Derived | I24: tbl_project_task_milestone; mapping; tasks | J24: Not Applicable – Non-Direct Support | K24: No milestone status field; completion must be inferred from mapped tasks. | M24: Pending | N24: Not applicable: schema support is not Direct. | P24: tbl_project_task_milestone | Q24: No Data (Table Empty) | R24: Blocked — No Data + Business Rule
A25: 24 | B25: Milestones | C25: next_project_milestone | D25: What is the next milestone for :project_name? | E25: Show the nearest upcoming milestone for :project_name. | F25: Which milestone comes next for :project_name? | G25: project_name | H25: Direct | I25: milestone tables | J25: Mapped – Direct Schema | K25: Use earliest future end date. | L25: SELECT DISTINCT m.milestone_id, m.milestone, m.start_date, m.end_date FROM tbl_project_task_milestone m JOIN tbl_project_task_milestone_mapping mm ON mm.milestone_id = m.milestone_id JOIN tbl_projects p ON p.project_id = mm.project_id WHERE p.title = :project_name AND m.end_date >= CURRENT_DATE ORDER BY m.end_date LIMIT 1; | M25: Pending | N25: Mapped from schema | P25: tbl_project_task_milestone, tbl_project_task_milestone_mapping | Q25: No Data (Table Empty) | R25: Dead — Milestone Module Unused
A26: 25 | B26: Milestones | C26: milestone_tasks | D26: Which tasks belong to milestone :milestone_name? | E26: Show tasks mapped to :milestone_name. | F26: List the work items under :milestone_name. | G26: milestone_name, project_name | H26: Direct | I26: tbl_project_task_milestone_mapping; tbl_project_tasks | J26: Mapped – Direct Schema | K26: Project name may be required to disambiguate duplicate milestone names. | L26: SELECT p.project_id, p.title AS project_title, m.milestone_id, m.milestone, t.task_id, t.reference_no, t.title AS task_title, t.start_date, t.due_date, ts.status_name, t.percent_complete FROM tbl_project_task_milestone m JOIN tbl_project_task_milestone_mapping mm ON mm.milestone_id = m.milestone_id JOIN tbl_project_tasks t ON t.task_id = mm.task_id JOIN tbl_projects p ON p.project_id = mm.project_id LEFT JOIN tbl_project_task_status ts ON ts.task_status_id = t.task_status_id WHERE m.milestone = :milestone_name AND t.status = 1 AND t.archive = 0 ORDER BY p.title, t.due_date, t.reference_no; | M26: Pending | N26: Mapped from schema | P26: tbl_project_task_milestone, tbl_project_task_milestone_mapping | Q26: No Data (Table Empty) | R26: Dead — Milestone Module Unused
A27: 26 | B27: Milestones | C27: milestone_task_progress | D27: What is the task completion progress of milestone :milestone_name? | E27: How many milestone tasks are completed? | F27: Show completed versus open tasks for :milestone_name. | G27: milestone_name, project_name | H27: Derived | I27: mapping; tasks; task status | J27: Not Applicable – Non-Direct Support | K27: Define closed task statuses. | M27: Pending | N27: Not applicable: schema support is not Direct. | P27: — | Q27: N/A | R27: Blocked — Business Rule / Schema Gap
A28: 27 | B28: Milestones | C28: milestones_without_tasks | D28: Which milestones have no mapped tasks? | E28: Show empty milestones. | F28: List milestones that are not linked to work items. | G28: none | H28: Direct | I28: milestone tables | J28: Mapped – Direct Schema | K28: Straight anti-join. | L28: SELECT m.milestone_id, m.milestone, m.start_date, m.end_date FROM tbl_project_task_milestone m LEFT JOIN tbl_project_task_milestone_mapping mm ON mm.milestone_id = m.milestone_id WHERE mm.task_id IS NULL ORDER BY m.end_date, m.milestone; | M28: Pending | N28: Mapped from schema | P28: tbl_project_task_milestone, tbl_project_task_milestone_mapping | Q28: No Data (Table Empty) | R28: Dead — Milestone Module Unused
A29: 28 | B29: Milestones | C29: milestone_date_slippage | D29: Which milestone dates differ from their mapped task dates? | E29: Show milestones with task schedules outside milestone dates. | F29: List milestone schedule mismatches. | G29: none | H29: Derived | I29: milestone tables; mapping | J29: Not Applicable – Non-Direct Support | K29: No baseline milestone date exists; this is schedule consistency, not baseline slippage. | M29: Pending | N29: Not applicable: schema support is not Direct. | P29: — | Q29: N/A | R29: Blocked — Business Rule / Schema Gap
A30: 29 | B30: Milestones | C30: milestones_due_month | D30: Which milestones are due this month? | E30: Show this month’s milestone deadlines. | F30: List milestones ending this month. | G30: month | H30: Direct | I30: tbl_project_task_milestone.end_date | J30: Mapped – Direct Schema | K30: Use organization timezone. | L30: SELECT DISTINCT p.project_id, p.project_key, p.title AS project_title, m.milestone_id, m.milestone, m.end_date FROM tbl_project_task_milestone m JOIN tbl_project_task_milestone_mapping mm ON mm.milestone_id = m.milestone_id JOIN tbl_projects p ON p.project_id = mm.project_id WHERE m.end_date >= DATE_FORMAT(CURRENT_DATE, '%Y-%m-01') AND m.end_date < DATE_ADD(LAST_DAY(CURRENT_DATE), INTERVAL 1 DAY) ORDER BY m.end_date, p.title; | M30: Pending | N30: Mapped from schema | P30: tbl_project_task_milestone, tbl_project_task_milestone_mapping | Q30: No Data (Table Empty) | R30: Dead — Milestone Module Unused
A31: 30 | B31: Milestones | C31: milestone_owner | D31: Who owns milestone :milestone_name? | E31: Show the owner of :milestone_name. | F31: Who is responsible for :milestone_name? | G31: milestone_name | H31: Not supported directly | I31: milestone tables | J31: Not Applicable – Non-Direct Support | K31: No owner column exists on milestone table; may be inferred from task owners only. | M31: Pending | N31: Not applicable: schema support is not Direct. | P31: — | Q31: N/A | R31: Blocked — Business Rule / Schema Gap
A32: 31 | B32: Tasks | C32: my_open_tasks | D32: What are my open tasks? | E32: Show tasks assigned to me that are not closed. | F32: List my pending work items. | G32: current_user | H32: Direct | I32: tbl_project_task_users; tbl_project_tasks; task status | J32: Not Mapped – Business Rule Required | K32: Define open status types and whether task_owner also counts. | M32: Pending | N32: Not mapped: “open” status types and whether task_owner counts are business rules. | O32: SELECT t.task_id, t.title, t.due_date, t.priority, t.project_id, ts.status_name FROM tbl_project_tasks t INNER JOIN tbl_project_task_users tu ON t.task_id = tu.task_id INNER JOIN tbl_project_task_status ts ON t.task_status_id = ts.task_status_id WHERE tu.user_id = {your_user_id} AND ts.status_type != 3 ORDER BY t.due_date ASC | P32: — | Q32: N/A | R32: Blocked — Business Rule / Schema Gap
A33: 32 | B33: Tasks | C33: my_tasks_due_today | D33: Which of my tasks are due today? | E33: Show my tasks with today’s due date. | F33: What work is due for me today? | G33: current_user, current_date | H33: Direct | I33: task users; tasks | J33: Mapped – Direct Schema | K33: Use organization timezone. | L33: SELECT t.task_id, t.reference_no, t.title, p.title AS project_title, t.due_date, ts.status_name, t.priority, t.rag, t.percent_complete FROM tbl_project_task_users tu JOIN tbl_project_tasks t ON t.task_id = tu.task_id JOIN tbl_projects p ON p.project_id = t.project_id LEFT JOIN tbl_project_task_status ts ON ts.task_status_id = t.task_status_id WHERE tu.user_id = :current_user_id AND tu.status = 1 AND t.status = 1 AND t.archive = 0 AND DATE(t.due_date) = CURRENT_DATE ORDER BY t.due_date, t.reference_no; | M33: Pending | N33: Mapped from schema | P33: — | Q33: Data Available | R33: Ready for Verification
A34: 33 | B34: Tasks | C34: my_overdue_tasks | D34: Which of my tasks are overdue? | E34: Show my delayed tasks. | F34: List my open tasks past their due date. | G34: current_user, as_of_date | H34: Derived | I34: task users; tasks; task status | J34: Not Applicable – Non-Direct Support | K34: Define open statuses. | M34: Pending | N34: Not applicable: schema support is not Direct. | P34: — | Q34: N/A | R34: Blocked — Business Rule / Schema Gap
A35: 34 | B35: Tasks | C35: tasks_assigned_to_user | D35: Show tasks assigned to :employee_name. | E35: List :employee_name’s tasks. | F35: What work is assigned to :employee_name? | G35: employee_name | H35: Direct | I35: tbl_project_task_users; tbl_users; tasks | J35: Mapped – Direct Schema | K35: Handle active assignment status. | L35: SELECT u.user_id, CONCAT_WS(' ', u.first_name, u.last_name) AS employee_name, p.title AS project_title, t.task_id, t.reference_no, t.title AS task_title, t.due_date, ts.status_name, tu.allot_percentage FROM tbl_users u JOIN tbl_project_task_users tu ON tu.user_id = u.user_id JOIN tbl_project_tasks t ON t.task_id = tu.task_id JOIN tbl_projects p ON p.project_id = t.project_id LEFT JOIN tbl_project_task_status ts ON ts.task_status_id = t.task_status_id WHERE CONCAT_WS(' ', u.first_name, u.last_name) = :employee_name AND tu.status = 1 AND t.status = 1 AND t.archive = 0 ORDER BY p.title, t.due_date, t.reference_no; | M35: Pending | N35: Mapped from schema | P35: — | Q35: Data Available | R35: Ready for Verification
A36: 35 | B36: Tasks | C36: project_open_tasks | D36: Show open tasks for :project_name. | E36: List pending tasks under :project_name. | F36: What work remains for :project_name? | G36: project_name | H36: Derived | I36: tasks; task status | J36: Not Applicable – Non-Direct Support | K36: Define open statuses. | M36: Pending | N36: Not applicable: schema support is not Direct. | P36: — | Q36: N/A | R36: Blocked — Business Rule / Schema Gap
A37: 36 | B37: Tasks | C37: project_closed_tasks | D37: Show completed tasks for :project_name. | E37: List closed tasks under :project_name. | F37: What tasks are finished in :project_name? | G37: project_name | H37: Derived | I37: tasks; task status | J37: Not Applicable – Non-Direct Support | K37: Define closed status types. | M37: Pending | N37: Not applicable: schema support is not Direct. | P37: — | Q37: N/A | R37: Blocked — Business Rule / Schema Gap
A38: 37 | B38: Tasks | C38: unassigned_tasks | D38: Which tasks are unassigned? | E38: Show tasks with no active assignee. | F38: List unallocated tasks. | G38: project_scope | H38: Derived | I38: tasks; task users | J38: Not Applicable – Non-Direct Support | K38: Confirm whether task_owner is an assignment. | M38: Pending | N38: Not applicable: schema support is not Direct. | P38: — | Q38: N/A | R38: Blocked — Business Rule / Schema Gap
A39: 38 | B39: Tasks | C39: high_priority_tasks | D39: Show high-priority open tasks. | E39: List urgent pending tasks. | F39: Which open tasks have high priority? | G39: project_scope | H39: Derived | I39: tasks.priority; task status | J39: Not Applicable – Non-Direct Support | K39: Confirm priority values. | M39: Pending | N39: Not applicable: schema support is not Direct. | P39: — | Q39: N/A | R39: Blocked — Business Rule / Schema Gap
A40: 39 | B40: Tasks | C40: red_rag_tasks | D40: Which tasks have a red RAG status? | E40: Show red-health tasks. | F40: List tasks flagged red. | G40: project_scope | H40: Direct | I40: tbl_project_tasks.rag | J40: Mapped – Direct Schema | K40: Confirm stored RAG values. | L40: SELECT t.task_id, t.reference_no, t.title, p.title AS project_title, t.rag, t.due_date, ts.status_name FROM tbl_project_tasks t JOIN tbl_projects p ON p.project_id = t.project_id LEFT JOIN tbl_project_task_status ts ON ts.task_status_id = t.task_status_id WHERE LOWER(t.rag) = 'red' AND t.status = 1 AND t.archive = 0 ORDER BY t.due_date, p.title; | M40: Pending | N40: Mapped from schema | P40: — | Q40: Data Available | R40: Ready for Verification
A41: 40 | B41: Tasks | C41: tasks_due_period | D41: Which tasks are due between :start_date and :end_date? | E41: Show tasks due in the selected period. | F41: List upcoming task deadlines. | G41: start_date, end_date | H41: Direct | I41: tbl_project_tasks.due_date | J41: Mapped – Direct Schema | K41: Default visibility scope required. | L41: SELECT t.task_id, t.reference_no, t.title, p.title AS project_title, t.due_date, ts.status_name, t.priority, t.rag FROM tbl_project_tasks t JOIN tbl_projects p ON p.project_id = t.project_id LEFT JOIN tbl_project_task_status ts ON ts.task_status_id = t.task_status_id WHERE t.due_date >= :start_date AND t.due_date < DATE_ADD(:end_date, INTERVAL 1 DAY) AND t.status = 1 AND t.archive = 0 ORDER BY t.due_date, p.title, t.reference_no; | M41: Pending | N41: Mapped from schema | P41: — | Q41: Data Available | R41: Ready for Verification
A42: 41 | B42: Tasks | C42: task_details | D42: Show details of task :task_reference. | E42: Give me the task summary for :task_reference. | F42: Open task :task_reference. | G42: task_reference | H42: Direct | I42: tbl_project_tasks | J42: Mapped – Direct Schema | K42: Prefer reference_no over title. | L42: SELECT t.task_id, t.reference_no, t.title, t.description, p.project_id, p.title AS project_title, t.task_owner, t.start_date, t.due_date, t.task_status_id, ts.status_name, t.priority, t.rag, t.estimate, t.actual_hours, t.percent_complete, t.update_date FROM tbl_project_tasks t JOIN tbl_projects p ON p.project_id = t.project_id LEFT JOIN tbl_project_task_status ts ON ts.task_status_id = t.task_status_id WHERE t.reference_no = :task_reference AND t.status = 1 AND t.archive = 0; | M42: Pending | N42: Mapped from schema | P42: — | Q42: Data Available | R42: Ready for Verification
A43: 42 | B43: Tasks | C43: subtasks_of_task | D43: Show subtasks of :task_reference. | E43: List child tasks under :task_reference. | F43: What tasks depend hierarchically on :task_reference? | G43: task_reference | H43: Direct | I43: tbl_project_tasks.parent_id | J43: Mapped – Direct Schema | K43: Hierarchy only; not dependency semantics. | L43: SELECT c.task_id, c.reference_no, c.title, c.start_date, c.due_date, ts.status_name, c.priority, c.rag, c.percent_complete FROM tbl_project_tasks parent JOIN tbl_project_tasks c ON c.parent_id = parent.task_id LEFT JOIN tbl_project_task_status ts ON ts.task_status_id = c.task_status_id WHERE parent.reference_no = :task_reference AND c.status = 1 AND c.archive = 0 ORDER BY c.due_date, c.reference_no; | M43: Pending | N43: Mapped from schema | P43: — | Q43: Data Available | R43: Ready for Verification
A44: 43 | B44: Tasks | C44: task_assignees | D44: Who is assigned to task :task_reference? | E44: Show all assignees for :task_reference. | F44: Which users are allocated to :task_reference? | G44: task_reference | H44: Direct | I44: tbl_project_task_users; tbl_users | J44: Mapped – Direct Schema | K44: Include allot_percentage. | L44: SELECT u.user_id, CONCAT_WS(' ', u.first_name, u.last_name) AS employee_name, u.email, tu.allot_percentage, tu.post_date AS assigned_on FROM tbl_project_tasks t JOIN tbl_project_task_users tu ON tu.task_id = t.task_id JOIN tbl_users u ON u.user_id = tu.user_id WHERE t.reference_no = :task_reference AND tu.status = 1 ORDER BY employee_name; | M44: Pending | N44: Mapped from schema | P44: — | Q44: Data Available | R44: Ready for Verification
A45: 44 | B45: Tasks | C45: task_allocation_percentages | D45: Show allocation percentages for task :task_reference. | E45: How is task :task_reference allocated? | F45: List assignees and percentages for :task_reference. | G45: task_reference | H45: Direct | I45: tbl_project_task_users.allot_percentage | J45: Mapped – Direct Schema | K45: Confirm whether total may exceed 100%. | L45: SELECT u.user_id, CONCAT_WS(' ', u.first_name, u.last_name) AS employee_name, tu.allot_percentage FROM tbl_project_tasks t JOIN tbl_project_task_users tu ON tu.task_id = t.task_id JOIN tbl_users u ON u.user_id = tu.user_id WHERE t.reference_no = :task_reference AND tu.status = 1 ORDER BY tu.allot_percentage DESC, employee_name; | M45: Pending | N45: Mapped from schema | P45: — | Q45: Data Available | R45: Ready for Verification
A46: 45 | B46: Tasks | C46: tasks_without_due_date | D46: Which open tasks have no due date? | E46: Show pending tasks missing deadlines. | F46: List tasks without a due date. | G46: project_scope | H46: Derived | I46: tasks; task status | J46: Not Applicable – Non-Direct Support | K46: Define open statuses. | M46: Pending | N46: Not applicable: schema support is not Direct. | P46: — | Q46: N/A | R46: Blocked — Business Rule / Schema Gap
A47: 46 | B47: Tasks | C47: task_progress | D47: What is the completion percentage of task :task_reference? | E47: Show progress for :task_reference. | F47: How complete is :task_reference? | G47: task_reference | H47: Direct | I47: tbl_project_tasks.percent_complete | J47: Mapped – Direct Schema | K47: Validate scale 0–100. | L47: SELECT t.task_id, t.reference_no, t.title, t.percent_complete, ts.status_name, t.update_date FROM tbl_project_tasks t LEFT JOIN tbl_project_task_status ts ON ts.task_status_id = t.task_status_id WHERE t.reference_no = :task_reference AND t.status = 1 AND t.archive = 0; | M47: Pending | N47: Mapped from schema | P47: — | Q47: Data Available | R47: Ready for Verification
A48: 47 | B48: Tasks | C48: task_estimate_vs_actual | D48: Compare estimate and actual hours for task :task_reference. | E48: Show planned versus actual effort for :task_reference. | F48: Is :task_reference over its estimate? | G48: task_reference | H48: Direct | I48: tbl_project_tasks.estimate; actual_hours | J48: Mapped – Direct Schema | K48: Confirm units. | L48: SELECT t.task_id, t.reference_no, t.title, t.estimate AS estimated_hours, t.actual_hours, (t.actual_hours - t.estimate) AS variance_hours, t.estimate_complete AS remaining_estimate_hours FROM tbl_project_tasks t WHERE t.reference_no = :task_reference AND t.status = 1 AND t.archive = 0; | M48: Pending | N48: Mapped from schema | P48: — | Q48: Data Available | R48: Ready for Verification
A49: 48 | B49: Tasks | C49: tasks_over_estimate | D49: Which tasks have exceeded their estimated hours? | E49: Show tasks where actual hours are above estimate. | F49: List effort-overrun tasks. | G49: project_scope | H49: Derived | I49: tbl_project_tasks.estimate; actual_hours | J49: Not Applicable – Non-Direct Support | K49: Null/zero estimate handling. | M49: Pending | N49: Not applicable: schema support is not Direct. | P49: — | Q49: N/A | R49: Blocked — Business Rule / Schema Gap
A50: 49 | B50: Tasks | C50: recently_updated_tasks | D50: Which tasks were updated in the last :days days? | E50: Show recently changed tasks. | F50: List tasks updated recently. | G50: days | H50: Direct | I50: tbl_project_tasks.update_date | J50: Mapped – Direct Schema | K50: Visibility scope required. | L50: SELECT t.task_id, t.reference_no, t.title, p.title AS project_title, t.update_date, ts.status_name, t.percent_complete FROM tbl_project_tasks t JOIN tbl_projects p ON p.project_id = t.project_id LEFT JOIN tbl_project_task_status ts ON ts.task_status_id = t.task_status_id WHERE t.update_date >= DATE_SUB(NOW(), INTERVAL :days DAY) AND t.status = 1 AND t.archive = 0 ORDER BY t.update_date DESC; | M50: Pending | N50: Mapped from schema | P50: — | Q50: Data Available | R50: Ready for Verification
A51: 50 | B51: Tasks | C51: stale_open_tasks | D51: Which open tasks have not been updated in :days days? | E51: Show stale pending tasks. | F51: List inactive open tasks. | G51: days | H51: Derived | I51: tasks; task status | J51: Not Applicable – Non-Direct Support | K51: Define open statuses. | M51: Pending | N51: Not applicable: schema support is not Direct. | P51: — | Q51: N/A | R51: Blocked — Business Rule / Schema Gap
A52: 51 | B52: Tasks | C52: task_status_counts | D52: Show task counts by status for :project_name. | E52: Summarize tasks by workflow status for :project_name. | F52: How many tasks are in each status for :project_name? | G52: project_name | H52: Direct | I52: tasks; task status | J52: Mapped – Direct Schema | K52: Lookup data required. | L52: SELECT ts.task_status_id, ts.status_name, ts.status_type, COUNT(*) AS task_count FROM tbl_project_tasks t JOIN tbl_projects p ON p.project_id = t.project_id LEFT JOIN tbl_project_task_status ts ON ts.task_status_id = t.task_status_id WHERE p.title = :project_name AND t.status = 1 AND t.archive = 0 GROUP BY ts.task_status_id, ts.status_name, ts.status_type ORDER BY ts.status_order, ts.status_name; | M52: Pending | N52: Mapped from schema | P52: — | Q52: Data Available | R52: Ready for Verification
A53: 52 | B53: Tasks | C53: task_workload_by_user | D53: Show task workload by user for :project_name. | E53: How many tasks does each person have on :project_name? | F53: Summarize assigned tasks by team member. | G53: project_name | H53: Derived | I53: tasks; task users; users | J53: Not Applicable – Non-Direct Support | K53: Define whether workload means count, estimate, or allocation percentage. | M53: Pending | N53: Not applicable: schema support is not Direct. | P53: — | Q53: N/A | R53: Blocked — Business Rule / Schema Gap
A54: 53 | B54: Timesheets | C54: my_logged_hours_today | D54: How many hours did I log today? | E54: Show my time entries for today. | F54: What is my total logged time today? | G54: current_user, current_date | H54: Direct | I54: tbl_timesheets | J54: Mapped – Direct Schema | K54: Combine hours and minutes. | L54: SELECT ts.user_id, ts.timesheet_date, SUM(ts.hours * 60 + ts.minutes) / 60.0 AS total_hours FROM tbl_timesheets ts WHERE ts.user_id = :current_user_id AND ts.timesheet_date = CURRENT_DATE GROUP BY ts.user_id, ts.timesheet_date; | M54: Pending | N54: Mapped from schema | P54: — | Q54: Data Available | R54: Ready for Verification
A55: 54 | B55: Timesheets | C55: my_logged_hours_period | D55: How many hours did I log between :start_date and :end_date? | E55: Show my logged time for the selected period. | F55: Total my timesheet hours for the period. | G55: current_user, start_date, end_date | H55: Direct | I55: tbl_timesheets | J55: Mapped – Direct Schema | K55: Combine hours and minutes. | L55: SELECT ts.user_id, SUM(ts.hours * 60 + ts.minutes) / 60.0 AS total_hours FROM tbl_timesheets ts WHERE ts.user_id = :current_user_id AND ts.timesheet_date BETWEEN :start_date AND :end_date GROUP BY ts.user_id; | M55: Pending | N55: Mapped from schema | P55: — | Q55: Data Available | R55: Ready for Verification
A56: 55 | B56: Timesheets | C56: employee_logged_hours | D56: Show hours logged by :employee_name between :start_date and :end_date. | E56: How much time did :employee_name record? | F56: List :employee_name’s timesheet total. | G56: employee_name, start_date, end_date | H56: Direct | I56: tbl_timesheets; tbl_users | J56: Mapped – Direct Schema | K56: RBAC needed for manager access. | L56: SELECT u.user_id, CONCAT_WS(' ', u.first_name, u.last_name) AS employee_name, SUM(ts.hours * 60 + ts.minutes) / 60.0 AS total_hours FROM tbl_users u JOIN tbl_timesheets ts ON ts.user_id = u.user_id WHERE CONCAT_WS(' ', u.first_name, u.last_name) = :employee_name AND ts.timesheet_date BETWEEN :start_date AND :end_date GROUP BY u.user_id, u.first_name, u.last_name; | M56: Pending | N56: Mapped from schema | P56: — | Q56: Data Available | R56: Ready for Verification
A57: 56 | B57: Timesheets | C57: project_logged_hours | D57: How many hours were logged on :project_name between :start_date and :end_date? | E57: Show total project time for the period. | F57: What is the booked effort on :project_name? | G57: project_name, start_date, end_date | H57: Direct | I57: tbl_timesheets; tasks; projects | J57: Mapped – Direct Schema | K57: Timesheet links to project through task. | L57: SELECT p.project_id, p.title AS project_title, SUM(ts.hours * 60 + ts.minutes) / 60.0 AS total_hours FROM tbl_timesheets ts JOIN tbl_project_tasks t ON t.task_id = ts.task_id JOIN tbl_projects p ON p.project_id = t.project_id WHERE p.title = :project_name AND ts.timesheet_date BETWEEN :start_date AND :end_date GROUP BY p.project_id, p.title; | M57: Pending | N57: Mapped from schema | P57: — | Q57: Data Available | R57: Ready for Verification
A58: 57 | B58: Timesheets | C58: project_hours_by_user | D58: Show hours by user for :project_name. | E58: Who logged how much time on :project_name? | F58: Break down project hours by team member. | G58: project_name, start_date, end_date | H58: Direct | I58: timesheets; tasks; users | J58: Mapped – Direct Schema | K58: Date period should be mandatory or defaulted. | L58: SELECT u.user_id, CONCAT_WS(' ', u.first_name, u.last_name) AS employee_name, SUM(ts.hours * 60 + ts.minutes) / 60.0 AS total_hours FROM tbl_timesheets ts JOIN tbl_project_tasks t ON t.task_id = ts.task_id JOIN tbl_projects p ON p.project_id = t.project_id JOIN tbl_users u ON u.user_id = ts.user_id WHERE p.title = :project_name AND ts.timesheet_date BETWEEN :start_date AND :end_date GROUP BY u.user_id, u.first_name, u.last_name ORDER BY total_hours DESC; | M58: Pending | N58: Mapped from schema | P58: — | Q58: Data Available | R58: Ready for Verification
A59: 58 | B59: Timesheets | C59: hours_by_task | D59: How many hours were logged against task :task_reference? | E59: Show booked time for :task_reference. | F59: What is the total effort recorded on :task_reference? | G59: task_reference, start_date, end_date | H59: Direct | I59: tbl_timesheets; tasks | J59: Mapped – Direct Schema | K59: Combine hours and minutes. | L59: SELECT t.task_id, t.reference_no, t.title, SUM(ts.hours * 60 + ts.minutes) / 60.0 AS total_hours FROM tbl_project_tasks t LEFT JOIN tbl_timesheets ts ON ts.task_id = t.task_id WHERE t.reference_no = :task_reference GROUP BY t.task_id, t.reference_no, t.title; | M59: Pending | N59: Mapped from schema | P59: — | Q59: Data Available | R59: Ready for Verification
A60: 59 | B60: Timesheets | C60: timesheet_entries_by_task_type | D60: Show logged hours by project task type. | E60: Break down timesheet hours by task type. | F60: How much time was recorded for each task type? | G60: start_date, end_date | H60: Partial | I60: tbl_timesheets.project_task_type_id | J60: Not Applicable – Non-Direct Support | K60: Task-type reference table must be confirmed. | M60: Pending | N60: Not applicable: schema support is not Direct. | P60: — | Q60: N/A | R60: Blocked — Business Rule / Schema Gap
A61: 60 | B61: Timesheets | C61: users_without_time_entries | D61: Who has no timesheet entries for :date? | E61: Show users who did not log time on :date. | F61: List missing time entries for :date. | G61: date, population_scope | H61: Derived | I61: tbl_users; tbl_timesheets | J61: Not Applicable – Non-Direct Support | K61: Define expected population, working days, leave, and active users. | M61: Pending | N61: Not applicable: schema support is not Direct. | P61: — | Q61: N/A | R61: Blocked — Business Rule / Schema Gap
A62: 61 | B62: Timesheets | C62: daily_hours_above_threshold | D62: Who logged more than :hours_threshold hours on :date? | E62: Show high-hour timesheet entries. | F62: List users exceeding the daily-hours threshold. | G62: date, hours_threshold | H62: Derived | I62: tbl_timesheets; users | J62: Not Applicable – Non-Direct Support | K62: Threshold supplied at runtime. | M62: Pending | N62: Not applicable: schema support is not Direct. | P62: — | Q62: N/A | R62: Blocked — Business Rule / Schema Gap
A63: 62 | B63: Timesheets | C63: project_hours_vs_task_actual | D63: Compare timesheet hours with task actual hours for :project_name. | E63: Show discrepancies between booked time and task actual hours. | F63: Do task actuals match timesheet totals? | G63: project_name | H63: Derived | I63: tbl_timesheets; tbl_project_tasks.actual_hours | J63: Not Applicable – Non-Direct Support | K63: Clarify whether actual_hours is system-calculated or manually maintained. | M63: Pending | N63: Not applicable: schema support is not Direct. | P63: — | Q63: N/A | R63: Blocked — Business Rule / Schema Gap
A64: 63 | B64: Timesheets | C64: timesheet_approval_status | D64: What is the approval status of my timesheet? | E64: Show whether my timesheet is approved. | F64: Are my time entries pending approval? | G64: current_user, period | H64: Not supported directly | I64: tbl_timesheets | J64: Not Applicable – Non-Direct Support | K64: No approval/status field is present in tbl_timesheets. | M64: Pending | N64: Not applicable: schema support is not Direct. | P64: — | Q64: N/A | R64: Blocked — Business Rule / Schema Gap
A65: 64 | B65: Timesheets | C65: rejected_timesheets | D65: Which timesheets were rejected? | E65: Show rejected time entries. | F65: List declined timesheets. | G65: period | H65: Not supported directly | I65: tbl_timesheets | J65: Not Applicable – Non-Direct Support | K65: No rejection field or workflow table identified. | M65: Pending | N65: Not applicable: schema support is not Direct. | P65: — | Q65: N/A | R65: Blocked — Business Rule / Schema Gap
A66: 65 | B66: Resources | C66: my_project_allocations | D66: What projects am I allocated to? | E66: Show my current project allocations. | F66: List projects where I am a member. | G66: current_user, as_of_date | H66: Direct | I66: tbl_project_users; projects | J66: Mapped – Direct Schema | K66: Use allocation dates and active status. | L66: SELECT p.project_id, p.project_key, p.title, pu.access_type, pu.role_id, pu.allocation_from, pu.allocation_to, pu.allocation_hrs, pu.resource_type, pu.request_status FROM tbl_project_users pu JOIN tbl_projects p ON p.project_id = pu.project_id WHERE pu.user_id = :current_user_id AND pu.status = 1 AND pu.request_status = 'A' ORDER BY pu.allocation_from DESC, p.title; | M66: Pending | N66: Mapped from schema | P66: — | Q66: Data Available | R66: Ready for Verification
A67: 66 | B67: Resources | C67: employee_allocations | D67: Show allocations for :employee_name. | E67: Which projects is :employee_name allocated to? | F67: List :employee_name’s project assignments. | G67: employee_name, as_of_date | H67: Direct | I67: tbl_project_users; users; projects | J67: Mapped – Direct Schema | K67: RBAC required. | L67: SELECT u.user_id, CONCAT_WS(' ', u.first_name, u.last_name) AS employee_name, p.project_id, p.title AS project_title, pu.allocation_from, pu.allocation_to, pu.allocation_hrs, pu.resource_type, pu.access_type, pu.request_status FROM tbl_users u JOIN tbl_project_users pu ON pu.user_id = u.user_id JOIN tbl_projects p ON p.project_id = pu.project_id WHERE CONCAT_WS(' ', u.first_name, u.last_name) = :employee_name AND pu.status = 1 ORDER BY pu.allocation_from DESC, p.title; | M67: Pending | N67: Mapped from schema | P67: — | Q67: Data Available | R67: Ready for Verification
A68: 67 | B68: Resources | C68: project_team | D68: Who is allocated to :project_name? | E68: Show the team of :project_name. | F68: List project members for :project_name. | G68: project_name | H68: Direct | I68: tbl_project_users; users | J68: Mapped – Direct Schema | K68: Filter active allocation and request status. | L68: SELECT u.user_id, CONCAT_WS(' ', u.first_name, u.last_name) AS employee_name, u.email, pu.access_type, pu.role_id, pu.allocation_from, pu.allocation_to, pu.allocation_hrs, pu.resource_type, pu.request_status FROM tbl_projects p JOIN tbl_project_users pu ON pu.project_id = p.project_id JOIN tbl_users u ON u.user_id = pu.user_id WHERE p.title = :project_name AND pu.status = 1 ORDER BY employee_name; | M68: Pending | N68: Mapped from schema | P68: — | Q68: Data Available | R68: Ready for Verification
A69: 68 | B69: Resources | C69: project_allocated_hours | D69: Show allocated hours by user for :project_name. | E69: How many hours is each user allocated to :project_name? | F69: List resource allocation hours for :project_name. | G69: project_name | H69: Direct | I69: tbl_project_users.allocation_hrs | J69: Mapped – Direct Schema | K69: Confirm allocation_hrs period basis. | L69: SELECT u.user_id, CONCAT_WS(' ', u.first_name, u.last_name) AS employee_name, pu.allocation_hrs, pu.allocation_from, pu.allocation_to, pu.resource_type FROM tbl_projects p JOIN tbl_project_users pu ON pu.project_id = p.project_id JOIN tbl_users u ON u.user_id = pu.user_id WHERE p.title = :project_name AND pu.status = 1 AND pu.request_status = 'A' ORDER BY pu.allocation_hrs DESC, employee_name; | M69: Pending | N69: Mapped from schema | P69: — | Q69: Data Available | R69: Ready for Verification
A70: 69 | B70: Resources | C70: allocations_ending_soon | D70: Whose project allocation ends in the next :days days? | E70: Show allocations ending soon. | F70: List users rolling off projects soon. | G70: days | H70: Direct | I70: tbl_project_users.allocation_to | J70: Mapped – Direct Schema | K70: Active allocation filter required. | L70: SELECT u.user_id, CONCAT_WS(' ', u.first_name, u.last_name) AS employee_name, p.project_id, p.title AS project_title, pu.allocation_to, pu.allocation_hrs, pu.resource_type FROM tbl_project_users pu JOIN tbl_projects p ON p.project_id = pu.project_id JOIN tbl_users u ON u.user_id = pu.user_id WHERE pu.status = 1 AND pu.request_status = 'A' AND pu.allocation_to >= CURRENT_DATE AND pu.allocation_to < DATE_ADD(CURRENT_DATE, INTERVAL :days + 1 DAY) ORDER BY pu.allocation_to, employee_name; | M70: Pending | N70: Mapped from schema | P70: — | Q70: Data Available | R70: Ready for Verification
A71: 70 | B71: Resources | C71: allocations_starting_soon | D71: Whose project allocation starts in the next :days days? | E71: Show upcoming allocations. | F71: List users joining projects soon. | G71: days | H71: Direct | I71: tbl_project_users.allocation_from | J71: Mapped – Direct Schema | K71: Active/request status filter required. | L71: SELECT u.user_id, CONCAT_WS(' ', u.first_name, u.last_name) AS employee_name, p.project_id, p.title AS project_title, pu.allocation_from, pu.allocation_to, pu.allocation_hrs, pu.resource_type FROM tbl_project_users pu JOIN tbl_projects p ON p.project_id = pu.project_id JOIN tbl_users u ON u.user_id = pu.user_id WHERE pu.status = 1 AND pu.request_status IN ('A','I') AND pu.allocation_from >= CURRENT_DATE AND pu.allocation_from < DATE_ADD(CURRENT_DATE, INTERVAL :days + 1 DAY) ORDER BY pu.allocation_from, employee_name; | M71: Pending | N71: Mapped from schema | P71: — | Q71: Data Available | R71: Ready for Verification
A72: 71 | B72: Resources | C72: resources_by_department | D72: Show active users in department :department_name. | E72: List department resources. | F72: Who belongs to :department_name? | G72: department_name | H72: Partial | I72: tbl_users; department relationships | J72: Not Applicable – Non-Direct Support | K72: tbl_users does not expose a direct department_id in visible columns. | M72: Pending | N72: Not applicable: schema support is not Direct. | P72: — | Q72: N/A | R72: Blocked — Business Rule / Schema Gap
A73: 72 | B73: Resources | C73: resources_by_team | D73: Show active users in team :team_name. | E73: List users in :team_name. | F73: Who belongs to :team_name? | G73: team_name | H73: Partial | I73: tbl_project_team; project users; users | J73: Not Applicable – Non-Direct Support | K73: No direct team-user table identified in PMS subset. | M73: Pending | N73: Not applicable: schema support is not Direct. | P73: tbl_project_team | Q73: No Data (Table Empty) | R73: Blocked — No Data + Business Rule
A74: 73 | B74: Resources | C74: resource_skills | D74: What skills does :employee_name have? | E74: Show :employee_name’s recorded skills. | F74: List skills for :employee_name. | G74: employee_name | H74: Direct | I74: tbl_user_skills; skill master to identify | J74: Mapped – Direct Schema | K74: Skill reference table must be located/confirmed. | L74: SELECT u.user_id, CONCAT_WS(' ', u.first_name, u.last_name) AS employee_name, s.id AS skill_id, s.name AS skill_name FROM tbl_users u JOIN tbl_user_skills us ON us.user_id = u.user_id JOIN tbl_master_skills s ON s.id = us.skill_id WHERE CONCAT_WS(' ', u.first_name, u.last_name) = :employee_name AND us.status = '1' AND s.status = '1' ORDER BY s.name; | M74: Pending | N74: Mapped from schema | P74: — | Q74: Data Available | R74: Ready for Verification
A75: 74 | B75: Resources | C75: available_by_skill | D75: Who with skill :skill_name is available between :start_date and :end_date? | E75: Find resources with :skill_name and no overlapping allocation. | F75: Show available :skill_name resources. | G75: skill_name, start_date, end_date | H75: Derived | I75: tbl_user_skills; tbl_project_users | J75: Not Applicable – Non-Direct Support | K75: Define availability and allocation capacity. | M75: Pending | N75: Not applicable: schema support is not Direct. | P75: — | Q75: N/A | R75: Blocked — Business Rule / Schema Gap
A76: 75 | B76: Resources | C76: overlapping_allocations | D76: Which users have overlapping project allocations? | E76: Show resource allocation conflicts. | F76: List people assigned to overlapping project periods. | G76: date_range | H76: Derived | I76: tbl_project_users | J76: Not Applicable – Non-Direct Support | K76: Does not prove overallocation unless hours/capacity are defined. | M76: Pending | N76: Not applicable: schema support is not Direct. | P76: — | Q76: N/A | R76: Blocked — Business Rule / Schema Gap
A77: 76 | B77: Resources | C77: project_roles | D77: Show project roles for :project_name. | E77: List users and role IDs on :project_name. | F77: Who has which role on :project_name? | G77: project_name | H77: Direct | I77: tbl_project_users.role_id; role master | J77: Mapped – Direct Schema | K77: Role labels require lookup table. | L77: SELECT u.user_id, CONCAT_WS(' ', u.first_name, u.last_name) AS employee_name, pu.role_id, r.role_name, r.role_slug FROM tbl_projects p JOIN tbl_project_users pu ON pu.project_id = p.project_id JOIN tbl_users u ON u.user_id = pu.user_id LEFT JOIN tbl_roles r ON r.role_id = pu.role_id WHERE p.title = :project_name AND pu.status = 1 ORDER BY r.role_name, employee_name; | M77: Pending | N77: Mapped from schema | P77: — | Q77: Data Available | R77: Ready for Verification
A78: 77 | B78: Resources | C78: project_access_types | D78: Show access types for users on :project_name. | E78: Who has what access on :project_name? | F78: List project membership access levels. | G78: project_name | H78: Direct | I78: tbl_project_users.access_type | J78: Mapped – Direct Schema | K78: Enumerated values not available in schema. | L78: SELECT pu.access_type, COUNT(*) AS user_count FROM tbl_projects p JOIN tbl_project_users pu ON pu.project_id = p.project_id WHERE p.title = :project_name AND pu.status = 1 GROUP BY pu.access_type ORDER BY pu.access_type; | M78: Pending | N78: Mapped from schema | P78: — | Q78: Data Available | R78: Ready for Verification
A79: 78 | B79: Resources | C79: bench_resources | D79: Who is currently on the bench? | E79: Show users with no active project allocation. | F79: List unallocated active resources. | G79: as_of_date, population_scope | H79: Derived | I79: tbl_users; tbl_project_users | J79: Not Applicable – Non-Direct Support | K79: Define active employee population and whether no allocation means bench. | M79: Pending | N79: Not applicable: schema support is not Direct. | P79: — | Q79: N/A | R79: Blocked — Business Rule / Schema Gap
A80: 79 | B80: Utilization | C80: allocation_utilization_user | D80: What is :employee_name’s allocation utilization for :period? | E80: Show allocated hours versus capacity for :employee_name. | F80: How utilized is :employee_name based on allocations? | G80: employee_name, period | H80: Partial | I80: tbl_project_users.allocation_hrs | J80: Not Applicable – Non-Direct Support | K80: Capacity/working-hour calendar is not defined. | M80: Pending | N80: Not applicable: schema support is not Direct. | P80: — | Q80: N/A | R80: Blocked — Business Rule / Schema Gap
A81: 80 | B81: Utilization | C81: timesheet_utilization_user | D81: What is :employee_name’s timesheet utilization for :period? | E81: Show logged hours versus available hours for :employee_name. | F81: How utilized is :employee_name based on timesheets? | G81: employee_name, period | H81: Partial | I81: tbl_timesheets | J81: Not Applicable – Non-Direct Support | K81: Working hours and leave calendar required. | M81: Pending | N81: Not applicable: schema support is not Direct. | P81: — | Q81: N/A | R81: Blocked — Business Rule / Schema Gap
A82: 81 | B82: Utilization | C82: project_resource_utilization | D82: Show utilization of resources on :project_name. | E82: How utilized is the team on :project_name? | F82: List project utilization by member. | G82: project_name, period | H82: Partial | I82: project users; timesheets; tasks | J82: Not Applicable – Non-Direct Support | K82: Choose allocation-based or timesheet-based method. | M82: Pending | N82: Not applicable: schema support is not Direct. | P82: — | Q82: N/A | R82: Blocked — Business Rule / Schema Gap
A83: 82 | B83: Utilization | C83: low_utilization_users | D83: Who is below :threshold_percent utilization in :period? | E83: Show underutilized resources. | F83: List users below the utilization threshold. | G83: threshold_percent, period | H83: Partial | I83: project users; timesheets | J83: Not Applicable – Non-Direct Support | K83: Capacity and population rules required. | M83: Pending | N83: Not applicable: schema support is not Direct. | P83: — | Q83: N/A | R83: Blocked — Business Rule / Schema Gap
A84: 83 | B84: Utilization | C84: high_utilization_users | D84: Who is above :threshold_percent utilization in :period? | E84: Show highly utilized resources. | F84: List users over the utilization threshold. | G84: threshold_percent, period | H84: Partial | I84: project users; timesheets | J84: Not Applicable – Non-Direct Support | K84: Capacity and overtime rules required. | M84: Pending | N84: Not applicable: schema support is not Direct. | P84: — | Q84: N/A | R84: Blocked — Business Rule / Schema Gap
A85: 84 | B85: Utilization | C85: allocation_conflicts | D85: Who has allocations exceeding available capacity? | E85: Show overallocated users. | F85: List resource capacity conflicts. | G85: period | H85: Partial | I85: tbl_project_users.allocation_hrs | J85: Not Applicable – Non-Direct Support | K85: Allocation hours period basis must be known. | M85: Pending | N85: Not applicable: schema support is not Direct. | P85: — | Q85: N/A | R85: Blocked — Business Rule / Schema Gap
A86: 85 | B86: Utilization | C86: idle_capacity | D86: How much idle capacity is available in :period? | E86: Show unused resource capacity. | F86: What capacity remains unallocated? | G86: period, population_scope | H86: Partial | I86: project users; users | J86: Not Applicable – Non-Direct Support | K86: Requires working calendar and eligible population. | M86: Pending | N86: Not applicable: schema support is not Direct. | P86: — | Q86: N/A | R86: Blocked — Business Rule / Schema Gap
A87: 86 | B87: Utilization | C87: utilization_by_role | D87: Show utilization by project role for :period. | E87: Compare resource utilization across roles. | F87: What is utilization by role? | G87: period | H87: Partial | I87: project users.role_id; timesheets | J87: Not Applicable – Non-Direct Support | K87: Role master and capacity formula required. | M87: Pending | N87: Not applicable: schema support is not Direct. | P87: — | Q87: N/A | R87: Blocked — Business Rule / Schema Gap
A88: 87 | B88: Utilization | C88: utilization_by_department | D88: Show utilization for department :department_name in :period. | E88: How utilized is :department_name? | F88: Give department utilization. | G88: department_name, period | H88: Partial | I88: users; project users; timesheets | J88: Not Applicable – Non-Direct Support | K88: User-department mapping must be confirmed. | M88: Pending | N88: Not applicable: schema support is not Direct. | P88: — | Q88: N/A | R88: Blocked — Business Rule / Schema Gap
A89: 88 | B89: Utilization | C89: forecast_utilization | D89: What is forecast utilization for :future_period? | E89: Show expected resource utilization next month. | F89: Forecast allocation-based utilization. | G89: future_period | H89: Partial | I89: tbl_project_users allocation dates/hours | J89: Not Applicable – Non-Direct Support | K89: Only allocation-based forecast appears possible from schema. | M89: Pending | N89: Not applicable: schema support is not Direct. | P89: — | Q89: N/A | R89: Blocked — Business Rule / Schema Gap
A90: 89 | B90: Estimation & Financials | C90: project_estimate | D90: What is the estimate for :project_name? | E90: Show the project estimate value. | F90: How much effort is estimated for :project_name? | G90: project_name | H90: Direct | I90: tbl_projects.estimate | J90: Mapped – Direct Schema | K90: Confirm whether estimate is hours, days, or cost. | L90: SELECT p.project_id, p.project_key, p.title, p.estimate AS estimated_hours, p.is_approved FROM tbl_projects p WHERE p.title = :project_name AND p.status = 1 AND p.archive = 0 ORDER BY p.project_id; | M90: Pending | N90: Mapped from schema | P90: — | Q90: Data Available | R90: Ready for Verification
A91: 90 | B91: Estimation & Financials | C91: project_hours_summary | D91: Show total booked and chargeable hours for :project_name. | E91: What are the booked versus chargeable hours? | F91: Summarize project hour totals. | G91: project_name | H91: Direct | I91: tbl_projects.total_hours_booked; total_chargable_hours | J91: Mapped – Direct Schema | K91: Confirm refresh/source logic. | L91: SELECT p.project_id, p.project_key, p.title, p.estimate AS estimated_hours, p.total_hours_booked, p.total_chargable_hours, p.grant_hours, p.combined_hours FROM tbl_projects p WHERE p.title = :project_name AND p.status = 1 AND p.archive = 0 ORDER BY p.project_id; | M91: Pending | N91: Mapped from schema | P91: — | Q91: Data Available | R91: Ready for Verification
A92: 91 | B92: Estimation & Financials | C92: project_grant_hours | D92: How many grant hours does :project_name have? | E92: Show available grant hours. | F92: What are the granted hours for :project_name? | G92: project_name | H92: Partial | I92: tbl_projects archive/backup grant_hours | J92: Not Applicable – Non-Direct Support | K92: grant_hours was visible in archive/backup; confirm current tbl_projects column. | M92: Pending | N92: Not applicable: schema support is not Direct. | P92: — | Q92: N/A | R92: Blocked — Business Rule / Schema Gap
A93: 92 | B93: Estimation & Financials | C93: project_deal_value | D93: What is the deal value of :project_name? | E93: Show the commercial value of :project_name. | F93: What value is recorded for :project_name? | G93: project_name | H93: Partial | I93: tbl_projects.deal_value | J93: Not Applicable – Non-Direct Support | K93: Confirm currency and financial RBAC. | M93: Pending | N93: Not applicable: schema support is not Direct. | P93: — | Q93: N/A | R93: Blocked — Business Rule / Schema Gap
A94: 93 | B94: Estimation & Financials | C94: project_estimation_versions | D94: Show estimation versions for :project_name. | E94: List all estimates created for :project_name. | F94: What estimation revisions exist? | G94: project_name | H94: Direct | I94: tbl_project_estimation | J94: Mapped – Direct Schema | K94: Use version and status. | L94: SELECT e.estimation_id, e.project_id, e.version, e.estimation_status_id, es.status_name, e.review, e.user_id, e.reviewer_id, e.posted_on, e.updated_on FROM tbl_projects p JOIN tbl_project_estimation e ON e.project_id = p.project_id LEFT JOIN tbl_project_estimation_status es ON es.rca_status_id = e.estimation_status_id WHERE p.title = :project_name AND e.status = 1 ORDER BY e.updated_on DESC, e.estimation_id DESC; | M94: Pending | N94: Mapped from schema | P94: tbl_project_estimation | Q94: No Data (Table Empty) | R94: Dead — Estimation Module Unused
A95: 94 | B95: Estimation & Financials | C95: project_estimation_status | D95: What is the estimation status for :project_name? | E95: Show whether the estimate is under review or approved. | F95: What stage is the project estimation in? | G95: project_name | H95: Direct | I95: tbl_project_estimation; estimation status | J95: Mapped – Direct Schema | K95: Lookup values required. | L95: SELECT e.estimation_id, e.version, e.estimation_status_id, es.status_name, es.status_type, e.review, e.updated_on FROM tbl_projects p JOIN tbl_project_estimation e ON e.project_id = p.project_id LEFT JOIN tbl_project_estimation_status es ON es.rca_status_id = e.estimation_status_id WHERE p.title = :project_name AND e.status = 1 ORDER BY e.updated_on DESC, e.estimation_id DESC; | M95: Pending | N95: Mapped from schema | P95: tbl_project_estimation | Q95: No Data (Table Empty) | R95: Dead — Estimation Module Unused
